Workbook
Name REPS: Team!$B$6:$B$8
Name SDRS: Team!$B$12:$B$14

Sheet Start here
A1: Commercial Control · Usual Digital
A2: Month cash, commissions, automatic ranking and dashboard. One copy per month.
A4: HOW TO USE
A6: 1. | B6: In Google Sheets: File > Make a copy. Duplicate the sheet each month (e.g., Sales July/26).
A7: 2. | B7: TEAM tab: check names, base salary, commission % and cash target for each rep and SDR. Everything yellow is editable.
A8: 3. | B8: SALES tab: each sale is a row. CASH PAID THIS MONTH = what the customer actually paid: if monthly, the installment; if upfront, the full value. Months = contract length (1 to 12).
A9: 4. | B9: On the same row, mark WHO BOOKED IT: Rep or SDR (and which SDR). Commissions calculate on their own, on the 1st month.
A10: 5. | B10: PANELS and RANKING update on their own with the month's CASH: how much each earns and who the champion is.
A11: 6. | B11: DASHBOARD: fill in ad spend and cost per lead. Leads, conversion, CAC, ROAS and ROI calculate instantly, all on what came in this month.
A13: CALCULATION RULES (IMPORTANT)
A15: Month cash | C15: EVERYTHING in the sheet uses what CAME IN this month. Monthly = the installment paid. Upfront = the full value. No projecting future months: if the customer cancels later, it doesn't contaminate the result.
A16: Blank type | C16: If Type is left blank, the sheet treats it as MONTHLY (contract = value × months; commission on the full value entered). Only select Upfront when the customer pays it all at once.
A17: Commission base | C17: Always the 1st MONTH's value: if Monthly, the installment itself; if Upfront, the value ÷ months (e.g., $21,000 over 3 months = $7,000 base). Upfront does NOT commission on the full value.
A18: Rep commission | C18: The rep's % (default 30%, editable in Team) on the 1st-month base.
A19: SDR commission | C19: If the meeting was booked by an SDR, they earn their % (default 10%, editable) on the 1st-month base.
A20: Targets | C20: Each rep's and SDR's target is on the month's CASH (what came in), not the contract.
A21: Total contract | C21: The 'Total contract' column is ONLY a reference to the contract size. It's not in any calculation.
A22: ROAS | C22: Month's cash ÷ ad spend.
A23: ROI | C23: (Cash − ad spend − payroll and commissions) ÷ (ad spend + payroll and commissions).
A25: Usual Digital · Internal sales control

Sheet Reps Panel
A1: Panel · Reps
A2: Everything on the month's CASH. Total payable = base salary + commissions (1st month).
A4: INDIVIDUAL RESULT THIS MONTH
A5: Indicator | B5: =Team!$B$6 | C5: =Team!$B$7 | D5: =Team!$B$8
A6: Name | B6: =Team!$B$6 | C6: =Team!$B$7 | D6: =Team!$B$8
A7: Deals closed | B7: =COUNTIFS(Sales!$B$5:$B$84,Team!$B$6,Sales!$F$5:$F$84,">0") | C7: =COUNTIFS(Sales!$B$5:$B$84,Team!$B$7,Sales!$F$5:$F$84,">0") | D7: =COUNTIFS(Sales!$B$5:$B$84,Team!$B$8,Sales!$F$5:$F$84,">0")
A8: Cash generated this month | B8: =SUMIFS(Sales!$F$5:$F$84,Sales!$B$5:$B$84,Team!$B$6) | C8: =SUMIFS(Sales!$F$5:$F$84,Sales!$B$5:$B$84,Team!$B$7) | D8: =SUMIFS(Sales!$F$5:$F$84,Sales!$B$5:$B$84,Team!$B$8)
A9: Average deal (cash) | B9: =IFERROR(SUMIFS(Sales!$F$5:$F$84,Sales!$B$5:$B$84,Team!$B$6)/MAX(COUNTIFS(Sales!$B$5:$B$84,Team!$B$6,Sales!$F$5:$F$84,">0"),1),0) | C9: =IFERROR(SUMIFS(Sales!$F$5:$F$84,Sales!$B$5:$B$84,Team!$B$7)/MAX(COUNTIFS(Sales!$B$5:$B$84,Team!$B$7,Sales!$F$5:$F$84,">0"),1),0) | D9: =IFERROR(SUMIFS(Sales!$F$5:$F$84,Sales!$B$5:$B$84,Team!$B$8)/MAX(COUNTIFS(Sales!$B$5:$B$84,Team!$B$8,Sales!$F$5:$F$84,">0"),1),0)
A10: Month commission | B10: =SUMIFS(Sales!$K$5:$K$84,Sales!$B$5:$B$84,Team!$B$6) | C10: =SUMIFS(Sales!$K$5:$K$84,Sales!$B$5:$B$84,Team!$B$7) | D10: =SUMIFS(Sales!$K$5:$K$84,Sales!$B$5:$B$84,Team!$B$8)
A11: Base salary | B11: =Team!$C$6 | C11: =Team!$C$7 | D11: =Team!$C$8
A12: TOTAL PAYABLE | B12: =Team!$C$6+SUMIFS(Sales!$K$5:$K$84,Sales!$B$5:$B$84,Team!$B$6) | C12: =Team!$C$7+SUMIFS(Sales!$K$5:$K$84,Sales!$B$5:$B$84,Team!$B$7) | D12: =Team!$C$8+SUMIFS(Sales!$K$5:$K$84,Sales!$B$5:$B$84,Team!$B$8)
A13: Cash target | B13: =Team!$E$6 | C13: =Team!$E$7 | D13: =Team!$E$8
A14: % of target | B14: =IFERROR(SUMIFS(Sales!$F$5:$F$84,Sales!$B$5:$B$84,Team!$B$6)/MAX(Team!$E$6,1),0) | C14: =IFERROR(SUMIFS(Sales!$F$5:$F$84,Sales!$B$5:$B$84,Team!$B$7)/MAX(Team!$E$7,1),0) | D14: =IFERROR(SUMIFS(Sales!$F$5:$F$84,Sales!$B$5:$B$84,Team!$B$8)/MAX(Team!$E$8,1),0)
A15: Progress | B15: =REPT("█",MIN(ROUND(IFERROR(SUMIFS(Sales!$F$5:$F$84,Sales!$B$5:$B$84,Team!$B$6)/MAX(Team!$E$6,1),0)*10,0),10))&REPT("░",MAX(10-ROUND(IFERROR(SUMIFS(Sales!$F$5:$F$84,Sales!$B$5:$B$84,Team!$B$6)/MAX(Team!$E$6,1),0)*10,0),0)) | C15: =REPT("█",MIN(ROUND(IFERROR(SUMIFS(Sales!$F$5:$F$84,Sales!$B$5:$B$84,Team!$B$7)/MAX(Team!$E$7,1),0)*10,0),10))&REPT("░",MAX(10-ROUND(IFERROR(SUMIFS(Sales!$F$5:$F$84,Sales!$B$5:$B$84,Team!$B$7)/MAX(Team!$E$7,1),0)*10,0),0)) | D15: =REPT("█",MIN(ROUND(IFERROR(SUMIFS(Sales!$F$5:$F$84,Sales!$B$5:$B$84,Team!$B$8)/MAX(Team!$E$8,1),0)*10,0),10))&REPT("░",MAX(10-ROUND(IFERROR(SUMIFS(Sales!$F$5:$F$84,Sales!$B$5:$B$84,Team!$B$8)/MAX(Team!$E$8,1),0)*10,0),0))

Sheet SDRs Panel
A1: Panel · SDRs
A2: Commission (default 10%) on the 1st month of sales booked by the SDR. Metrics on the month's CASH.
A4: INDIVIDUAL RESULT THIS MONTH
A5: Indicator | B5: =Team!$B$12 | C5: =Team!$B$13 | D5: =Team!$B$14
A6: Name | B6: =Team!$B$12 | C6: =Team!$B$13 | D6: =Team!$B$14
A7: Influenced deals | B7: =COUNTIFS(Sales!$J$5:$J$84,Team!$B$12,Sales!$I$5:$I$84,"SDR",Sales!$F$5:$F$84,">0") | C7: =COUNTIFS(Sales!$J$5:$J$84,Team!$B$13,Sales!$I$5:$I$84,"SDR",Sales!$F$5:$F$84,">0") | D7: =COUNTIFS(Sales!$J$5:$J$84,Team!$B$14,Sales!$I$5:$I$84,"SDR",Sales!$F$5:$F$84,">0")
A8: Influenced cash | B8: =SUMIFS(Sales!$F$5:$F$84,Sales!$J$5:$J$84,Team!$B$12,Sales!$I$5:$I$84,"SDR") | C8: =SUMIFS(Sales!$F$5:$F$84,Sales!$J$5:$J$84,Team!$B$13,Sales!$I$5:$I$84,"SDR") | D8: =SUMIFS(Sales!$F$5:$F$84,Sales!$J$5:$J$84,Team!$B$14,Sales!$I$5:$I$84,"SDR")
A9: Month commission | B9: =SUMIFS(Sales!$L$5:$L$84,Sales!$J$5:$J$84,Team!$B$12) | C9: =SUMIFS(Sales!$L$5:$L$84,Sales!$J$5:$J$84,Team!$B$13) | D9: =SUMIFS(Sales!$L$5:$L$84,Sales!$J$5:$J$84,Team!$B$14)
A10: Base salary | B10: =Team!$C$12 | C10: =Team!$C$13 | D10: =Team!$C$14
A11: TOTAL PAYABLE | B11: =Team!$C$12+SUMIFS(Sales!$L$5:$L$84,Sales!$J$5:$J$84,Team!$B$12) | C11: =Team!$C$13+SUMIFS(Sales!$L$5:$L$84,Sales!$J$5:$J$84,Team!$B$13) | D11: =Team!$C$14+SUMIFS(Sales!$L$5:$L$84,Sales!$J$5:$J$84,Team!$B$14)
A12: Target (influenced cash) | B12: =Team!$E$12 | C12: =Team!$E$13 | D12: =Team!$E$14
A13: % of target | B13: =IFERROR(SUMIFS(Sales!$F$5:$F$84,Sales!$J$5:$J$84,Team!$B$12,Sales!$I$5:$I$84,"SDR")/MAX(Team!$E$12,1),0) | C13: =IFERROR(SUMIFS(Sales!$F$5:$F$84,Sales!$J$5:$J$84,Team!$B$13,Sales!$I$5:$I$84,"SDR")/MAX(Team!$E$13,1),0) | D13: =IFERROR(SUMIFS(Sales!$F$5:$F$84,Sales!$J$5:$J$84,Team!$B$14,Sales!$I$5:$I$84,"SDR")/MAX(Team!$E$14,1),0)
A14: Progress | B14: =REPT("█",MIN(ROUND(IFERROR(SUMIFS(Sales!$F$5:$F$84,Sales!$J$5:$J$84,Team!$B$12,Sales!$I$5:$I$84,"SDR")/MAX(Team!$E$12,1),0)*10,0),10))&REPT("░",MAX(10-ROUND(IFERROR(SUMIFS(Sales!$F$5:$F$84,Sales!$J$5:$J$84,Team!$B$12,Sales!$I$5:$I$84,"SDR")/MAX(Team!$E$12,1),0)*10,0),0)) | C14: =REPT("█",MIN(ROUND(IFERROR(SUMIFS(Sales!$F$5:$F$84,Sales!$J$5:$J$84,Team!$B$13,Sales!$I$5:$I$84,"SDR")/MAX(Team!$E$13,1),0)*10,0),10))&REPT("░",MAX(10-ROUND(IFERROR(SUMIFS(Sales!$F$5:$F$84,Sales!$J$5:$J$84,Team!$B$13,Sales!$I$5:$I$84,"SDR")/MAX(Team!$E$13,1),0)*10,0),0)) | D14: =REPT("█",MIN(ROUND(IFERROR(SUMIFS(Sales!$F$5:$F$84,Sales!$J$5:$J$84,Team!$B$14,Sales!$I$5:$I$84,"SDR")/MAX(Team!$E$14,1),0)*10,0),10))&REPT("░",MAX(10-ROUND(IFERROR(SUMIFS(Sales!$F$5:$F$84,Sales!$J$5:$J$84,Team!$B$14,Sales!$I$5:$I$84,"SDR")/MAX(Team!$E$14,1),0)*10,0),0))

Sheet Ranking
A1: Sales Ranking · auto-updating
A2: The month's champion by CASH generated. Updates with every sale logged.
A4: REPS · CHAMPIONS OF THE MONTH | J4: helper
A5: Position | B5: Rep | C5: Deals | D5: Cash generated | J5: =Team!$B$6 | K5: =SUMIFS(Sales!$F$5:$F$84,Sales!$B$5:$B$84,Team!$B$6) | L5: =K5+3*0.0001
A6: 🥇 1st | B6: =INDEX($J$5:$J$7,MATCH(LARGE($L$5:$L$7,1),$L$5:$L$7,0)) | C6: =COUNTIFS(Sales!$B$5:$B$84,$B6,Sales!$F$5:$F$84,">0") | D6: =SUMIFS(Sales!$F$5:$F$84,Sales!$B$5:$B$84,$B6) | J6: =Team!$B$7 | K6: =SUMIFS(Sales!$F$5:$F$84,Sales!$B$5:$B$84,Team!$B$7) | L6: =K6+2*0.0001
A7: 🥈 2nd | B7: =INDEX($J$5:$J$7,MATCH(LARGE($L$5:$L$7,2),$L$5:$L$7,0)) | C7: =COUNTIFS(Sales!$B$5:$B$84,$B7,Sales!$F$5:$F$84,">0") | D7: =SUMIFS(Sales!$F$5:$F$84,Sales!$B$5:$B$84,$B7) | J7: =Team!$B$8 | K7: =SUMIFS(Sales!$F$5:$F$84,Sales!$B$5:$B$84,Team!$B$8) | L7: =K7+1*0.0001
A8: 🥉 3rd | B8: =INDEX($J$5:$J$7,MATCH(LARGE($L$5:$L$7,3),$L$5:$L$7,0)) | C8: =COUNTIFS(Sales!$B$5:$B$84,$B8,Sales!$F$5:$F$84,">0") | D8: =SUMIFS(Sales!$F$5:$F$84,Sales!$B$5:$B$84,$B8)
J9: =Team!$B$12 | K9: =SUMIFS(Sales!$F$5:$F$84,Sales!$J$5:$J$84,Team!$B$12,Sales!$I$5:$I$84,"SDR") | L9: =K9+3*0.0001
A10: SDRS · BOOKING CHAMPIONS THAT BECAME SALES | J10: =Team!$B$13 | K10: =SUMIFS(Sales!$F$5:$F$84,Sales!$J$5:$J$84,Team!$B$13,Sales!$I$5:$I$84,"SDR") | L10: =K10+2*0.0001
A11: Position | B11: SDR | C11: Influenced deals | D11: Influenced cash | J11: =Team!$B$14 | K11: =SUMIFS(Sales!$F$5:$F$84,Sales!$J$5:$J$84,Team!$B$14,Sales!$I$5:$I$84,"SDR") | L11: =K11+1*0.0001
A12: 🥇 1st | B12: =INDEX($J$9:$J$11,MATCH(LARGE($L$9:$L$11,1),$L$9:$L$11,0)) | C12: =COUNTIFS(Sales!$J$5:$J$84,$B12,Sales!$I$5:$I$84,"SDR",Sales!$F$5:$F$84,">0") | D12: =SUMIFS(Sales!$F$5:$F$84,Sales!$J$5:$J$84,$B12,Sales!$I$5:$I$84,"SDR")
A13: 🥈 2nd | B13: =INDEX($J$9:$J$11,MATCH(LARGE($L$9:$L$11,2),$L$9:$L$11,0)) | C13: =COUNTIFS(Sales!$J$5:$J$84,$B13,Sales!$I$5:$I$84,"SDR",Sales!$F$5:$F$84,">0") | D13: =SUMIFS(Sales!$F$5:$F$84,Sales!$J$5:$J$84,$B13,Sales!$I$5:$I$84,"SDR")
A14: 🥉 3rd | B14: =INDEX($J$9:$J$11,MATCH(LARGE($L$9:$L$11,3),$L$9:$L$11,0)) | C14: =COUNTIFS(Sales!$J$5:$J$84,$B14,Sales!$I$5:$I$84,"SDR",Sales!$F$5:$F$84,">0") | D14: =SUMIFS(Sales!$F$5:$F$84,Sales!$J$5:$J$84,$B14,Sales!$I$5:$I$84,"SDR")

Sheet Sales Dashboard
A1: Sales Dashboard · the month's cash on one screen
A2: Fill only the yellow cells (marketing). Everything calculates on what CAME IN this month.
A4: MONTH INPUTS (EDIT) | L4: helper
A5: Reference month | B5: July/2026 | D5: Ad spend | E5: 5000 | G5: Cost per lead ($) | H5: 25 | L5: Booked: SDR | M5: =SUMIFS(Sales!$F$5:$F$84,Sales!$I$5:$I$84,"SDR")
A6: Other sales costs | B6: 0 | D6: (tools, bonuses, prizes...) | L6: Booked: Rep | M6: =SUMIFS(Sales!$F$5:$F$84,Sales!$I$5:$I$84,"Rep")
A8: MONTH CASH | L8: Installments | M8: =SUM(Sales!$F$5:$F$84)-SUMIFS(Sales!$F$5:$F$84,Sales!$E$5:$E$84,"Upfront")
A9: =SUM(Sales!$F$5:$F$84) | C9: =COUNTIF(Sales!$F$5:$F$84,">0") | E9: =SUM(Sales!$F$5:$F$84)-SUMIFS(Sales!$F$5:$F$84,Sales!$E$5:$E$84,"Upfront") | G9: =SUMIFS(Sales!$F$5:$F$84,Sales!$E$5:$E$84,"Upfront") | I9: =IFERROR(SUM(Sales!$F$5:$F$84)/MAX(COUNTIF(Sales!$F$5:$F$84,">0"),1),0) | L9: Upfront | M9: =SUMIFS(Sales!$F$5:$F$84,Sales!$E$5:$E$84,"Upfront")
A10: CASH IN (month) | C10: Deals closed | E10: Recurring revenue (installments) | G10: Upfront revenue | I10: Average deal (cash)
A11: =IFERROR(SUM(Sales!$H$5:$H$84)/MAX(COUNTIF(Sales!$F$5:$F$84,">0"),1),0) | C11: =COUNTIFS(Sales!$I$5:$I$84,"SDR",Sales!$F$5:$F$84,">0") | E11: =COUNTIFS(Sales!$I$5:$I$84,"Rep",Sales!$F$5:$F$84,">0")
A12: Average MONTHLY deal (1st month; upfront ÷ months) | C12: Deals via SDR | E12: Deals direct from rep
A14: MARKETING FUNNEL AND EFFICIENCY
A15: =IFERROR(ROUND($E$5/MAX($H$5,0.01),0),0) | C15: =IFERROR(COUNTIF(Sales!$F$5:$F$84,">0")/MAX(ROUND($E$5/MAX($H$5,0.01),0),1),0) | E15: =IFERROR($E$5/MAX(COUNTIF(Sales!$F$5:$F$84,">0"),1),0) | G15: =IFERROR(SUM(Sales!$F$5:$F$84)/MAX($E$5,1),0) | I15: =IFERROR((SUM(Sales!$F$5:$F$84)-$E$5-((SUM(Team!$C$6:$C$8)+SUM(Team!$C$12:$C$14))+(SUM(Sales!$K$5:$K$84)+SUM(Sales!$L$5:$L$84))+$B$6))/MAX($E$5+((SUM(Team!$C$6:$C$8)+SUM(Team!$C$12:$C$14))+(SUM(Sales!$K$5:$K$84)+SUM(Sales!$L$5:$L$84))+$B$6),1),0)
A16: Leads generated | C16: Lead → sale conversion | E16: CAC (cost per sale) | G16: ROAS (cash ÷ spend) | I16: ROI (with payroll)
A18: SALES COSTS AND PROFIT (MONTH)
A19: =(SUM(Team!$C$6:$C$8)+SUM(Team!$C$12:$C$14)) | C19: =(SUM(Sales!$K$5:$K$84)+SUM(Sales!$L$5:$L$84)) | E19: =((SUM(Team!$C$6:$C$8)+SUM(Team!$C$12:$C$14))+(SUM(Sales!$K$5:$K$84)+SUM(Sales!$L$5:$L$84))+$B$6) | G19: =$E$5 | I19: =SUM(Sales!$F$5:$F$84)-$E$5-((SUM(Team!$C$6:$C$8)+SUM(Team!$C$12:$C$14))+(SUM(Sales!$K$5:$K$84)+SUM(Sales!$L$5:$L$84))+$B$6)
A20: Payroll (salaries) | C20: Month commissions | E20: Total sales cost | G20: Ad spend invested | I20: Month PROFIT (cash)
A22: CHARTS

Sheet Team
A1: Team · Salaries, Commissions and Targets
A2: Edit the yellow fields. Targets are month CASH. Names feed the dropdowns in the Sales tab.
A4: REPS (CLOSERS)
A5: # | B5: Name | C5: Base salary | D5: Commission % (1st month) | E5: Month cash target ($)
A6: 1 | B6: Rep 1 | C6: 2500 | D6: 0.3 | E6: 50000
A7: 2 | B7: Rep 2 | C7: 2500 | D7: 0.3 | E7: 50000
A8: 3 | B8: Rep 3 | C8: 2500 | D8: 0.3 | E8: 50000
A10: SDRS (PRE-SALES)
A11: # | B11: Name | C11: Base salary | D11: Commission % (1st month) | E11: Influenced cash target ($)
A12: 1 | B12: SDR 1 | C12: 1800 | D12: 0.1 | E12: 40000
A13: 2 | B13: SDR 2 | C13: 1800 | D13: 0.1 | E13: 40000
A14: 3 | B14: SDR 3 | C14: 1800 | D14: 0.1 | E14: 40000
A16: Tip: when you hire someone new, just change the name here and the dropdowns and panels follow.

Sheet Sales
A1: Sales This Month · logging
A2: One sale per row. CASH PAID THIS MONTH: if Monthly, enter the installment paid; if Upfront, the full value that came in. Months = contract length (max 12).
A4: Date | B4: Rep | C4: Customer | D4: Company | E4: Type | F4: Cash paid this month ($) | G4: Months | H4: Commission base (1st month) | I4: Who booked | J4: SDR (if SDR) | K4: Rep commission | L4: SDR commission | M4: Total contract (reference) | N4: Notes
H5: =IF($F5="","",ROUND(IF($E5="Upfront",$F5/IF($G5="",1,$G5),$F5),2)) | K5: =IF($F5="","",ROUND(IF($E5="Upfront",$F5/IF($G5="",1,$G5),$F5)*IFERROR(VLOOKUP($B5,Team!$B$6:$E$8,3,0),0),2)) | L5: =IF($F5="","",IF(AND($I5="SDR",$J5<>""),ROUND(IF($E5="Upfront",$F5/IF($G5="",1,$G5),$F5)*IFERROR(VLOOKUP($J5,Team!$B$12:$E$14,3,0),0),2),0)) | M5: =IF($F5="","",IF($E5="Upfront",$F5,$F5*IF($G5="",1,$G5)))
H6: =IF($F6="","",ROUND(IF($E6="Upfront",$F6/IF($G6="",1,$G6),$F6),2)) | K6: =IF($F6="","",ROUND(IF($E6="Upfront",$F6/IF($G6="",1,$G6),$F6)*IFERROR(VLOOKUP($B6,Team!$B$6:$E$8,3,0),0),2)) | L6: =IF($F6="","",IF(AND($I6="SDR",$J6<>""),ROUND(IF($E6="Upfront",$F6/IF($G6="",1,$G6),$F6)*IFERROR(VLOOKUP($J6,Team!$B$12:$E$14,3,0),0),2),0)) | M6: =IF($F6="","",IF($E6="Upfront",$F6,$F6*IF($G6="",1,$G6)))
H7: =IF($F7="","",ROUND(IF($E7="Upfront",$F7/IF($G7="",1,$G7),$F7),2)) | K7: =IF($F7="","",ROUND(IF($E7="Upfront",$F7/IF($G7="",1,$G7),$F7)*IFERROR(VLOOKUP($B7,Team!$B$6:$E$8,3,0),0),2)) | L7: =IF($F7="","",IF(AND($I7="SDR",$J7<>""),ROUND(IF($E7="Upfront",$F7/IF($G7="",1,$G7),$F7)*IFERROR(VLOOKUP($J7,Team!$B$12:$E$14,3,0),0),2),0)) | M7: =IF($F7="","",IF($E7="Upfront",$F7,$F7*IF($G7="",1,$G7)))
H8: =IF($F8="","",ROUND(IF($E8="Upfront",$F8/IF($G8="",1,$G8),$F8),2)) | K8: =IF($F8="","",ROUND(IF($E8="Upfront",$F8/IF($G8="",1,$G8),$F8)*IFERROR(VLOOKUP($B8,Team!$B$6:$E$8,3,0),0),2)) | L8: =IF($F8="","",IF(AND($I8="SDR",$J8<>""),ROUND(IF($E8="Upfront",$F8/IF($G8="",1,$G8),$F8)*IFERROR(VLOOKUP($J8,Team!$B$12:$E$14,3,0),0),2),0)) | M8: =IF($F8="","",IF($E8="Upfront",$F8,$F8*IF($G8="",1,$G8)))
H9: =IF($F9="","",ROUND(IF($E9="Upfront",$F9/IF($G9="",1,$G9),$F9),2)) | K9: =IF($F9="","",ROUND(IF($E9="Upfront",$F9/IF($G9="",1,$G9),$F9)*IFERROR(VLOOKUP($B9,Team!$B$6:$E$8,3,0),0),2)) | L9: =IF($F9="","",IF(AND($I9="SDR",$J9<>""),ROUND(IF($E9="Upfront",$F9/IF($G9="",1,$G9),$F9)*IFERROR(VLOOKUP($J9,Team!$B$12:$E$14,3,0),0),2),0)) | M9: =IF($F9="","",IF($E9="Upfront",$F9,$F9*IF($G9="",1,$G9)))
H10: =IF($F10="","",ROUND(IF($E10="Upfront",$F10/IF($G10="",1,$G10),$F10),2)) | K10: =IF($F10="","",ROUND(IF($E10="Upfront",$F10/IF($G10="",1,$G10),$F10)*IFERROR(VLOOKUP($B10,Team!$B$6:$E$8,3,0),0),2)) | L10: =IF($F10="","",IF(AND($I10="SDR",$J10<>""),ROUND(IF($E10="Upfront",$F10/IF($G10="",1,$G10),$F10)*IFERROR(VLOOKUP($J10,Team!$B$12:$E$14,3,0),0),2),0)) | M10: =IF($F10="","",IF($E10="Upfront",$F10,$F10*IF($G10="",1,$G10)))
H11: =IF($F11="","",ROUND(IF($E11="Upfront",$F11/IF($G11="",1,$G11),$F11),2)) | K11: =IF($F11="","",ROUND(IF($E11="Upfront",$F11/IF($G11="",1,$G11),$F11)*IFERROR(VLOOKUP($B11,Team!$B$6:$E$8,3,0),0),2)) | L11: =IF($F11="","",IF(AND($I11="SDR",$J11<>""),ROUND(IF($E11="Upfront",$F11/IF($G11="",1,$G11),$F11)*IFERROR(VLOOKUP($J11,Team!$B$12:$E$14,3,0),0),2),0)) | M11: =IF($F11="","",IF($E11="Upfront",$F11,$F11*IF($G11="",1,$G11)))
H12: =IF($F12="","",ROUND(IF($E12="Upfront",$F12/IF($G12="",1,$G12),$F12),2)) | K12: =IF($F12="","",ROUND(IF($E12="Upfront",$F12/IF($G12="",1,$G12),$F12)*IFERROR(VLOOKUP($B12,Team!$B$6:$E$8,3,0),0),2)) | L12: =IF($F12="","",IF(AND($I12="SDR",$J12<>""),ROUND(IF($E12="Upfront",$F12/IF($G12="",1,$G12),$F12)*IFERROR(VLOOKUP($J12,Team!$B$12:$E$14,3,0),0),2),0)) | M12: =IF($F12="","",IF($E12="Upfront",$F12,$F12*IF($G12="",1,$G12)))
H13: =IF($F13="","",ROUND(IF($E13="Upfront",$F13/IF($G13="",1,$G13),$F13),2)) | K13: =IF($F13="","",ROUND(IF($E13="Upfront",$F13/IF($G13="",1,$G13),$F13)*IFERROR(VLOOKUP($B13,Team!$B$6:$E$8,3,0),0),2)) | L13: =IF($F13="","",IF(AND($I13="SDR",$J13<>""),ROUND(IF($E13="Upfront",$F13/IF($G13="",1,$G13),$F13)*IFERROR(VLOOKUP($J13,Team!$B$12:$E$14,3,0),0),2),0)) | M13: =IF($F13="","",IF($E13="Upfront",$F13,$F13*IF($G13="",1,$G13)))
H14: =IF($F14="","",ROUND(IF($E14="Upfront",$F14/IF($G14="",1,$G14),$F14),2)) | K14: =IF($F14="","",ROUND(IF($E14="Upfront",$F14/IF($G14="",1,$G14),$F14)*IFERROR(VLOOKUP($B14,Team!$B$6:$E$8,3,0),0),2)) | L14: =IF($F14="","",IF(AND($I14="SDR",$J14<>""),ROUND(IF($E14="Upfront",$F14/IF($G14="",1,$G14),$F14)*IFERROR(VLOOKUP($J14,Team!$B$12:$E$14,3,0),0),2),0)) | M14: =IF($F14="","",IF($E14="Upfront",$F14,$F14*IF($G14="",1,$G14)))
H15: =IF($F15="","",ROUND(IF($E15="Upfront",$F15/IF($G15="",1,$G15),$F15),2)) | K15: =IF($F15="","",ROUND(IF($E15="Upfront",$F15/IF($G15="",1,$G15),$F15)*IFERROR(VLOOKUP($B15,Team!$B$6:$E$8,3,0),0),2)) | L15: =IF($F15="","",IF(AND($I15="SDR",$J15<>""),ROUND(IF($E15="Upfront",$F15/IF($G15="",1,$G15),$F15)*IFERROR(VLOOKUP($J15,Team!$B$12:$E$14,3,0),0),2),0)) | M15: =IF($F15="","",IF($E15="Upfront",$F15,$F15*IF($G15="",1,$G15)))
H16: =IF($F16="","",ROUND(IF($E16="Upfront",$F16/IF($G16="",1,$G16),$F16),2)) | K16: =IF($F16="","",ROUND(IF($E16="Upfront",$F16/IF($G16="",1,$G16),$F16)*IFERROR(VLOOKUP($B16,Team!$B$6:$E$8,3,0),0),2)) | L16: =IF($F16="","",IF(AND($I16="SDR",$J16<>""),ROUND(IF($E16="Upfront",$F16/IF($G16="",1,$G16),$F16)*IFERROR(VLOOKUP($J16,Team!$B$12:$E$14,3,0),0),2),0)) | M16: =IF($F16="","",IF($E16="Upfront",$F16,$F16*IF($G16="",1,$G16)))
... H84: =IF($F84="","",ROUND(IF($E84="Upfront",$F84/IF($G84="",1,$G84),$F84),2)) | K84: =IF($F84="","",ROUND(IF($E84="Upfront",$F84/IF($G84="",1,$G84),$F84)*IFERROR(VLOOKUP($B84,Team!$B$6:$E$8,3,0),0),2)) | L84: =IF($F84="","",IF(AND($I84="SDR",$J84<>""),ROUND(IF($E84="Upfront",$F84/IF($G84="",1,$G84),$F84)*IFERROR(VLOOKUP($J84,Team!$B$12:$E$14,3,0),0),2),0)) | M84: =IF($F84="","",IF($E84="Upfront",$F84,$F84*IF($G84="",1,$G84)))
A85: TOTAL (month cash) | F85: =SUM(F5:F84) | K85: =SUM(K5:K84) | L85: =SUM(L5:L84)
