Workbook

Sheet Start here
A1: MONEY MANAGEMENT SHEET · USUAL DIGITAL
A2: A bonus to organize your finances and make your money work.
B5: How to use
B7: 1. Go to each month (January to December tabs) and log your Income and Expenses.
B8: 2. Use the dropdowns to pick Category, Payment method and Yes/No.
B9: 3. Totals, balance and the by-category charts are calculated automatically.
B10: 4. Track the whole year on the Annual Summary tab (it pulls everything from the months).
B11: 5. Set targets on the Financial Goals tab and track your Investments.
B12: 6. Save your favorite accounts on the Accounts tab.
B14: Golden tip
B15: Log expenses the same day. 5 minutes a day beats 3 hours at month-end. What's not measured isn't managed.
B17: Bonus by Gabriel Isidoro and Renan Paiva · Sales structuring specialists

Sheet Annual Summary
A1: ANNUAL SUMMARY · USUAL
A2: Values are pulled automatically from each month. No need to fill anything here.
B3: Income this year | C3: Expenses this year | D3: Balance this year | E3: % saved
B4: =C19 | C4: =D19 | D4: =E19 | E4: =IFERROR(E19/C19,0)
B6: Month | C6: Income | D6: Expenses | E6: Balance | F6: % saved
B7: January | C7: ='January'!J4 | D7: ='January'!J5 | E7: =C7-D7 | F7: =IFERROR(E7/C7,0)
B8: February | C8: ='February'!J4 | D8: ='February'!J5 | E8: =C8-D8 | F8: =IFERROR(E8/C8,0)
B9: March | C9: ='March'!J4 | D9: ='March'!J5 | E9: =C9-D9 | F9: =IFERROR(E9/C9,0)
B10: April | C10: ='April'!J4 | D10: ='April'!J5 | E10: =C10-D10 | F10: =IFERROR(E10/C10,0)
B11: May | C11: ='May'!J4 | D11: ='May'!J5 | E11: =C11-D11 | F11: =IFERROR(E11/C11,0)
B12: June | C12: ='June'!J4 | D12: ='June'!J5 | E12: =C12-D12 | F12: =IFERROR(E12/C12,0)
B13: July | C13: ='July'!J4 | D13: ='July'!J5 | E13: =C13-D13 | F13: =IFERROR(E13/C13,0)
B14: August | C14: ='August'!J4 | D14: ='August'!J5 | E14: =C14-D14 | F14: =IFERROR(E14/C14,0)
B15: September | C15: ='September'!J4 | D15: ='September'!J5 | E15: =C15-D15 | F15: =IFERROR(E15/C15,0)
B16: October | C16: ='October'!J4 | D16: ='October'!J5 | E16: =C16-D16 | F16: =IFERROR(E16/C16,0)
B17: November | C17: ='November'!J4 | D17: ='November'!J5 | E17: =C17-D17 | F17: =IFERROR(E17/C17,0)
B18: December | C18: ='December'!J4 | D18: ='December'!J5 | E18: =C18-D18 | F18: =IFERROR(E18/C18,0)
B19: TOTAL | C19: =SUM(C7:C18) | D19: =SUM(D7:D18) | E19: =SUM(E7:E18) | F19: =IFERROR(E19/C19,0)

Sheet January
A1: JANUARY · Money Control · USUAL
A2: Fill in Income and Expenses. Use the dropdowns in the Category, Method and Yes/No columns.
A3: INCOME | I3: MONTH SUMMARY
A4: Date | B4: Description | C4: Category | D4: Method | E4: Amount | F4: Received? | I4: Income | J4: =E25
I5: Expenses | J5: =F69
I6: Balance | J6: =J4-J5
I7: % saved | J7: =IFERROR(J6/J4,0)
I9: EXPENSES BY CATEGORY
I10: Category | J10: Amount | K10: %
I11: Housing | J11: =SUMIF($C$29:$C$68,$I11,$F$29:$F$68) | K11: =IFERROR(J11/$F$69,0)
I12: Bills | J12: =SUMIF($C$29:$C$68,$I12,$F$29:$F$68) | K12: =IFERROR(J12/$F$69,0)
I13: Groceries | J13: =SUMIF($C$29:$C$68,$I13,$F$29:$F$68) | K13: =IFERROR(J13/$F$69,0)
I14: Dining | J14: =SUMIF($C$29:$C$68,$I14,$F$29:$F$68) | K14: =IFERROR(J14/$F$69,0)
I15: Transport | J15: =SUMIF($C$29:$C$68,$I15,$F$29:$F$68) | K15: =IFERROR(J15/$F$69,0)
I16: Health | J16: =SUMIF($C$29:$C$68,$I16,$F$29:$F$68) | K16: =IFERROR(J16/$F$69,0)
I17: Education | J17: =SUMIF($C$29:$C$68,$I17,$F$29:$F$68) | K17: =IFERROR(J17/$F$69,0)
I18: Leisure | J18: =SUMIF($C$29:$C$68,$I18,$F$29:$F$68) | K18: =IFERROR(J18/$F$69,0)
I19: Clothing | J19: =SUMIF($C$29:$C$68,$I19,$F$29:$F$68) | K19: =IFERROR(J19/$F$69,0)
I20: Beauty | J20: =SUMIF($C$29:$C$68,$I20,$F$29:$F$68) | K20: =IFERROR(J20/$F$69,0)
I21: Subscriptions | J21: =SUMIF($C$29:$C$68,$I21,$F$29:$F$68) | K21: =IFERROR(J21/$F$69,0)
I22: Gifts | J22: =SUMIF($C$29:$C$68,$I22,$F$29:$F$68) | K22: =IFERROR(J22/$F$69,0)
... I24: Investments | J24: =SUMIF($C$29:$C$68,$I24,$F$29:$F$68) | K24: =IFERROR(J24/$F$69,0)
A25: TOTAL INCOME | E25: =SUM(E5:E24) | I25: Debt | J25: =SUMIF($C$29:$C$68,$I25,$F$29:$F$68) | K25: =IFERROR(J25/$F$69,0)
I26: Other | J26: =SUMIF($C$29:$C$68,$I26,$F$29:$F$68) | K26: =IFERROR(J26/$F$69,0)
A27: EXPENSES
A28: Date | B28: Description | C28: Category | D28: Type | E28: Method | F28: Amount | G28: Paid? | I28: EXPENSES BY PAYMENT METHOD
I29: Card | J29: =SUMIF($E$29:$E$68,$I29,$F$29:$F$68)
I30: Debit | J30: =SUMIF($E$29:$E$68,$I30,$F$29:$F$68)
I31: Cash | J31: =SUMIF($E$29:$E$68,$I31,$F$29:$F$68)
I32: Transfer | J32: =SUMIF($E$29:$E$68,$I32,$F$29:$F$68)
I33: PayPal | J33: =SUMIF($E$29:$E$68,$I33,$F$29:$F$68)
I34: Check | J34: =SUMIF($E$29:$E$68,$I34,$F$29:$F$68)
A69: TOTAL EXPENSES | F69: =SUM(F29:F68)

Sheet February
A1: FEBRUARY · Money Control · USUAL
A2: Fill in Income and Expenses. Use the dropdowns in the Category, Method and Yes/No columns.
A3: INCOME | I3: MONTH SUMMARY
A4: Date | B4: Description | C4: Category | D4: Method | E4: Amount | F4: Received? | I4: Income | J4: =E25
I5: Expenses | J5: =F69
I6: Balance | J6: =J4-J5
I7: % saved | J7: =IFERROR(J6/J4,0)
I9: EXPENSES BY CATEGORY
I10: Category | J10: Amount | K10: %
I11: Housing | J11: =SUMIF($C$29:$C$68,$I11,$F$29:$F$68) | K11: =IFERROR(J11/$F$69,0)
I12: Bills | J12: =SUMIF($C$29:$C$68,$I12,$F$29:$F$68) | K12: =IFERROR(J12/$F$69,0)
I13: Groceries | J13: =SUMIF($C$29:$C$68,$I13,$F$29:$F$68) | K13: =IFERROR(J13/$F$69,0)
I14: Dining | J14: =SUMIF($C$29:$C$68,$I14,$F$29:$F$68) | K14: =IFERROR(J14/$F$69,0)
I15: Transport | J15: =SUMIF($C$29:$C$68,$I15,$F$29:$F$68) | K15: =IFERROR(J15/$F$69,0)
I16: Health | J16: =SUMIF($C$29:$C$68,$I16,$F$29:$F$68) | K16: =IFERROR(J16/$F$69,0)
I17: Education | J17: =SUMIF($C$29:$C$68,$I17,$F$29:$F$68) | K17: =IFERROR(J17/$F$69,0)
I18: Leisure | J18: =SUMIF($C$29:$C$68,$I18,$F$29:$F$68) | K18: =IFERROR(J18/$F$69,0)
I19: Clothing | J19: =SUMIF($C$29:$C$68,$I19,$F$29:$F$68) | K19: =IFERROR(J19/$F$69,0)
I20: Beauty | J20: =SUMIF($C$29:$C$68,$I20,$F$29:$F$68) | K20: =IFERROR(J20/$F$69,0)
I21: Subscriptions | J21: =SUMIF($C$29:$C$68,$I21,$F$29:$F$68) | K21: =IFERROR(J21/$F$69,0)
I22: Gifts | J22: =SUMIF($C$29:$C$68,$I22,$F$29:$F$68) | K22: =IFERROR(J22/$F$69,0)
... I24: Investments | J24: =SUMIF($C$29:$C$68,$I24,$F$29:$F$68) | K24: =IFERROR(J24/$F$69,0)
A25: TOTAL INCOME | E25: =SUM(E5:E24) | I25: Debt | J25: =SUMIF($C$29:$C$68,$I25,$F$29:$F$68) | K25: =IFERROR(J25/$F$69,0)
I26: Other | J26: =SUMIF($C$29:$C$68,$I26,$F$29:$F$68) | K26: =IFERROR(J26/$F$69,0)
A27: EXPENSES
A28: Date | B28: Description | C28: Category | D28: Type | E28: Method | F28: Amount | G28: Paid? | I28: EXPENSES BY PAYMENT METHOD
I29: Card | J29: =SUMIF($E$29:$E$68,$I29,$F$29:$F$68)
I30: Debit | J30: =SUMIF($E$29:$E$68,$I30,$F$29:$F$68)
I31: Cash | J31: =SUMIF($E$29:$E$68,$I31,$F$29:$F$68)
I32: Transfer | J32: =SUMIF($E$29:$E$68,$I32,$F$29:$F$68)
I33: PayPal | J33: =SUMIF($E$29:$E$68,$I33,$F$29:$F$68)
I34: Check | J34: =SUMIF($E$29:$E$68,$I34,$F$29:$F$68)
A69: TOTAL EXPENSES | F69: =SUM(F29:F68)

Sheet March
A1: MARCH · Money Control · USUAL
A2: Fill in Income and Expenses. Use the dropdowns in the Category, Method and Yes/No columns.
A3: INCOME | I3: MONTH SUMMARY
A4: Date | B4: Description | C4: Category | D4: Method | E4: Amount | F4: Received? | I4: Income | J4: =E25
I5: Expenses | J5: =F69
I6: Balance | J6: =J4-J5
I7: % saved | J7: =IFERROR(J6/J4,0)
I9: EXPENSES BY CATEGORY
I10: Category | J10: Amount | K10: %
I11: Housing | J11: =SUMIF($C$29:$C$68,$I11,$F$29:$F$68) | K11: =IFERROR(J11/$F$69,0)
I12: Bills | J12: =SUMIF($C$29:$C$68,$I12,$F$29:$F$68) | K12: =IFERROR(J12/$F$69,0)
I13: Groceries | J13: =SUMIF($C$29:$C$68,$I13,$F$29:$F$68) | K13: =IFERROR(J13/$F$69,0)
I14: Dining | J14: =SUMIF($C$29:$C$68,$I14,$F$29:$F$68) | K14: =IFERROR(J14/$F$69,0)
I15: Transport | J15: =SUMIF($C$29:$C$68,$I15,$F$29:$F$68) | K15: =IFERROR(J15/$F$69,0)
I16: Health | J16: =SUMIF($C$29:$C$68,$I16,$F$29:$F$68) | K16: =IFERROR(J16/$F$69,0)
I17: Education | J17: =SUMIF($C$29:$C$68,$I17,$F$29:$F$68) | K17: =IFERROR(J17/$F$69,0)
I18: Leisure | J18: =SUMIF($C$29:$C$68,$I18,$F$29:$F$68) | K18: =IFERROR(J18/$F$69,0)
I19: Clothing | J19: =SUMIF($C$29:$C$68,$I19,$F$29:$F$68) | K19: =IFERROR(J19/$F$69,0)
I20: Beauty | J20: =SUMIF($C$29:$C$68,$I20,$F$29:$F$68) | K20: =IFERROR(J20/$F$69,0)
I21: Subscriptions | J21: =SUMIF($C$29:$C$68,$I21,$F$29:$F$68) | K21: =IFERROR(J21/$F$69,0)
I22: Gifts | J22: =SUMIF($C$29:$C$68,$I22,$F$29:$F$68) | K22: =IFERROR(J22/$F$69,0)
... I24: Investments | J24: =SUMIF($C$29:$C$68,$I24,$F$29:$F$68) | K24: =IFERROR(J24/$F$69,0)
A25: TOTAL INCOME | E25: =SUM(E5:E24) | I25: Debt | J25: =SUMIF($C$29:$C$68,$I25,$F$29:$F$68) | K25: =IFERROR(J25/$F$69,0)
I26: Other | J26: =SUMIF($C$29:$C$68,$I26,$F$29:$F$68) | K26: =IFERROR(J26/$F$69,0)
A27: EXPENSES
A28: Date | B28: Description | C28: Category | D28: Type | E28: Method | F28: Amount | G28: Paid? | I28: EXPENSES BY PAYMENT METHOD
I29: Card | J29: =SUMIF($E$29:$E$68,$I29,$F$29:$F$68)
I30: Debit | J30: =SUMIF($E$29:$E$68,$I30,$F$29:$F$68)
I31: Cash | J31: =SUMIF($E$29:$E$68,$I31,$F$29:$F$68)
I32: Transfer | J32: =SUMIF($E$29:$E$68,$I32,$F$29:$F$68)
I33: PayPal | J33: =SUMIF($E$29:$E$68,$I33,$F$29:$F$68)
I34: Check | J34: =SUMIF($E$29:$E$68,$I34,$F$29:$F$68)
A69: TOTAL EXPENSES | F69: =SUM(F29:F68)

Sheet April
A1: APRIL · Money Control · USUAL
A2: Fill in Income and Expenses. Use the dropdowns in the Category, Method and Yes/No columns.
A3: INCOME | I3: MONTH SUMMARY
A4: Date | B4: Description | C4: Category | D4: Method | E4: Amount | F4: Received? | I4: Income | J4: =E25
I5: Expenses | J5: =F69
I6: Balance | J6: =J4-J5
I7: % saved | J7: =IFERROR(J6/J4,0)
I9: EXPENSES BY CATEGORY
I10: Category | J10: Amount | K10: %
I11: Housing | J11: =SUMIF($C$29:$C$68,$I11,$F$29:$F$68) | K11: =IFERROR(J11/$F$69,0)
I12: Bills | J12: =SUMIF($C$29:$C$68,$I12,$F$29:$F$68) | K12: =IFERROR(J12/$F$69,0)
I13: Groceries | J13: =SUMIF($C$29:$C$68,$I13,$F$29:$F$68) | K13: =IFERROR(J13/$F$69,0)
I14: Dining | J14: =SUMIF($C$29:$C$68,$I14,$F$29:$F$68) | K14: =IFERROR(J14/$F$69,0)
I15: Transport | J15: =SUMIF($C$29:$C$68,$I15,$F$29:$F$68) | K15: =IFERROR(J15/$F$69,0)
I16: Health | J16: =SUMIF($C$29:$C$68,$I16,$F$29:$F$68) | K16: =IFERROR(J16/$F$69,0)
I17: Education | J17: =SUMIF($C$29:$C$68,$I17,$F$29:$F$68) | K17: =IFERROR(J17/$F$69,0)
I18: Leisure | J18: =SUMIF($C$29:$C$68,$I18,$F$29:$F$68) | K18: =IFERROR(J18/$F$69,0)
I19: Clothing | J19: =SUMIF($C$29:$C$68,$I19,$F$29:$F$68) | K19: =IFERROR(J19/$F$69,0)
I20: Beauty | J20: =SUMIF($C$29:$C$68,$I20,$F$29:$F$68) | K20: =IFERROR(J20/$F$69,0)
I21: Subscriptions | J21: =SUMIF($C$29:$C$68,$I21,$F$29:$F$68) | K21: =IFERROR(J21/$F$69,0)
I22: Gifts | J22: =SUMIF($C$29:$C$68,$I22,$F$29:$F$68) | K22: =IFERROR(J22/$F$69,0)
... I24: Investments | J24: =SUMIF($C$29:$C$68,$I24,$F$29:$F$68) | K24: =IFERROR(J24/$F$69,0)
A25: TOTAL INCOME | E25: =SUM(E5:E24) | I25: Debt | J25: =SUMIF($C$29:$C$68,$I25,$F$29:$F$68) | K25: =IFERROR(J25/$F$69,0)
I26: Other | J26: =SUMIF($C$29:$C$68,$I26,$F$29:$F$68) | K26: =IFERROR(J26/$F$69,0)
A27: EXPENSES
A28: Date | B28: Description | C28: Category | D28: Type | E28: Method | F28: Amount | G28: Paid? | I28: EXPENSES BY PAYMENT METHOD
I29: Card | J29: =SUMIF($E$29:$E$68,$I29,$F$29:$F$68)
I30: Debit | J30: =SUMIF($E$29:$E$68,$I30,$F$29:$F$68)
I31: Cash | J31: =SUMIF($E$29:$E$68,$I31,$F$29:$F$68)
I32: Transfer | J32: =SUMIF($E$29:$E$68,$I32,$F$29:$F$68)
I33: PayPal | J33: =SUMIF($E$29:$E$68,$I33,$F$29:$F$68)
I34: Check | J34: =SUMIF($E$29:$E$68,$I34,$F$29:$F$68)
A69: TOTAL EXPENSES | F69: =SUM(F29:F68)

Sheet May
A1: MAY · Money Control · USUAL
A2: Fill in Income and Expenses. Use the dropdowns in the Category, Method and Yes/No columns.
A3: INCOME | I3: MONTH SUMMARY
A4: Date | B4: Description | C4: Category | D4: Method | E4: Amount | F4: Received? | I4: Income | J4: =E25
I5: Expenses | J5: =F69
I6: Balance | J6: =J4-J5
I7: % saved | J7: =IFERROR(J6/J4,0)
I9: EXPENSES BY CATEGORY
I10: Category | J10: Amount | K10: %
I11: Housing | J11: =SUMIF($C$29:$C$68,$I11,$F$29:$F$68) | K11: =IFERROR(J11/$F$69,0)
I12: Bills | J12: =SUMIF($C$29:$C$68,$I12,$F$29:$F$68) | K12: =IFERROR(J12/$F$69,0)
I13: Groceries | J13: =SUMIF($C$29:$C$68,$I13,$F$29:$F$68) | K13: =IFERROR(J13/$F$69,0)
I14: Dining | J14: =SUMIF($C$29:$C$68,$I14,$F$29:$F$68) | K14: =IFERROR(J14/$F$69,0)
I15: Transport | J15: =SUMIF($C$29:$C$68,$I15,$F$29:$F$68) | K15: =IFERROR(J15/$F$69,0)
I16: Health | J16: =SUMIF($C$29:$C$68,$I16,$F$29:$F$68) | K16: =IFERROR(J16/$F$69,0)
I17: Education | J17: =SUMIF($C$29:$C$68,$I17,$F$29:$F$68) | K17: =IFERROR(J17/$F$69,0)
I18: Leisure | J18: =SUMIF($C$29:$C$68,$I18,$F$29:$F$68) | K18: =IFERROR(J18/$F$69,0)
I19: Clothing | J19: =SUMIF($C$29:$C$68,$I19,$F$29:$F$68) | K19: =IFERROR(J19/$F$69,0)
I20: Beauty | J20: =SUMIF($C$29:$C$68,$I20,$F$29:$F$68) | K20: =IFERROR(J20/$F$69,0)
I21: Subscriptions | J21: =SUMIF($C$29:$C$68,$I21,$F$29:$F$68) | K21: =IFERROR(J21/$F$69,0)
I22: Gifts | J22: =SUMIF($C$29:$C$68,$I22,$F$29:$F$68) | K22: =IFERROR(J22/$F$69,0)
... I24: Investments | J24: =SUMIF($C$29:$C$68,$I24,$F$29:$F$68) | K24: =IFERROR(J24/$F$69,0)
A25: TOTAL INCOME | E25: =SUM(E5:E24) | I25: Debt | J25: =SUMIF($C$29:$C$68,$I25,$F$29:$F$68) | K25: =IFERROR(J25/$F$69,0)
I26: Other | J26: =SUMIF($C$29:$C$68,$I26,$F$29:$F$68) | K26: =IFERROR(J26/$F$69,0)
A27: EXPENSES
A28: Date | B28: Description | C28: Category | D28: Type | E28: Method | F28: Amount | G28: Paid? | I28: EXPENSES BY PAYMENT METHOD
I29: Card | J29: =SUMIF($E$29:$E$68,$I29,$F$29:$F$68)
I30: Debit | J30: =SUMIF($E$29:$E$68,$I30,$F$29:$F$68)
I31: Cash | J31: =SUMIF($E$29:$E$68,$I31,$F$29:$F$68)
I32: Transfer | J32: =SUMIF($E$29:$E$68,$I32,$F$29:$F$68)
I33: PayPal | J33: =SUMIF($E$29:$E$68,$I33,$F$29:$F$68)
I34: Check | J34: =SUMIF($E$29:$E$68,$I34,$F$29:$F$68)
A69: TOTAL EXPENSES | F69: =SUM(F29:F68)

Sheet June
A1: JUNE · Money Control · USUAL
A2: Fill in Income and Expenses. Use the dropdowns in the Category, Method and Yes/No columns.
A3: INCOME | I3: MONTH SUMMARY
A4: Date | B4: Description | C4: Category | D4: Method | E4: Amount | F4: Received? | I4: Income | J4: =E25
I5: Expenses | J5: =F69
I6: Balance | J6: =J4-J5
I7: % saved | J7: =IFERROR(J6/J4,0)
I9: EXPENSES BY CATEGORY
I10: Category | J10: Amount | K10: %
I11: Housing | J11: =SUMIF($C$29:$C$68,$I11,$F$29:$F$68) | K11: =IFERROR(J11/$F$69,0)
I12: Bills | J12: =SUMIF($C$29:$C$68,$I12,$F$29:$F$68) | K12: =IFERROR(J12/$F$69,0)
I13: Groceries | J13: =SUMIF($C$29:$C$68,$I13,$F$29:$F$68) | K13: =IFERROR(J13/$F$69,0)
I14: Dining | J14: =SUMIF($C$29:$C$68,$I14,$F$29:$F$68) | K14: =IFERROR(J14/$F$69,0)
I15: Transport | J15: =SUMIF($C$29:$C$68,$I15,$F$29:$F$68) | K15: =IFERROR(J15/$F$69,0)
I16: Health | J16: =SUMIF($C$29:$C$68,$I16,$F$29:$F$68) | K16: =IFERROR(J16/$F$69,0)
I17: Education | J17: =SUMIF($C$29:$C$68,$I17,$F$29:$F$68) | K17: =IFERROR(J17/$F$69,0)
I18: Leisure | J18: =SUMIF($C$29:$C$68,$I18,$F$29:$F$68) | K18: =IFERROR(J18/$F$69,0)
I19: Clothing | J19: =SUMIF($C$29:$C$68,$I19,$F$29:$F$68) | K19: =IFERROR(J19/$F$69,0)
I20: Beauty | J20: =SUMIF($C$29:$C$68,$I20,$F$29:$F$68) | K20: =IFERROR(J20/$F$69,0)
I21: Subscriptions | J21: =SUMIF($C$29:$C$68,$I21,$F$29:$F$68) | K21: =IFERROR(J21/$F$69,0)
I22: Gifts | J22: =SUMIF($C$29:$C$68,$I22,$F$29:$F$68) | K22: =IFERROR(J22/$F$69,0)
... I24: Investments | J24: =SUMIF($C$29:$C$68,$I24,$F$29:$F$68) | K24: =IFERROR(J24/$F$69,0)
A25: TOTAL INCOME | E25: =SUM(E5:E24) | I25: Debt | J25: =SUMIF($C$29:$C$68,$I25,$F$29:$F$68) | K25: =IFERROR(J25/$F$69,0)
I26: Other | J26: =SUMIF($C$29:$C$68,$I26,$F$29:$F$68) | K26: =IFERROR(J26/$F$69,0)
A27: EXPENSES
A28: Date | B28: Description | C28: Category | D28: Type | E28: Method | F28: Amount | G28: Paid? | I28: EXPENSES BY PAYMENT METHOD
I29: Card | J29: =SUMIF($E$29:$E$68,$I29,$F$29:$F$68)
I30: Debit | J30: =SUMIF($E$29:$E$68,$I30,$F$29:$F$68)
I31: Cash | J31: =SUMIF($E$29:$E$68,$I31,$F$29:$F$68)
I32: Transfer | J32: =SUMIF($E$29:$E$68,$I32,$F$29:$F$68)
I33: PayPal | J33: =SUMIF($E$29:$E$68,$I33,$F$29:$F$68)
I34: Check | J34: =SUMIF($E$29:$E$68,$I34,$F$29:$F$68)
A69: TOTAL EXPENSES | F69: =SUM(F29:F68)

Sheet July
A1: JULY · Money Control · USUAL
A2: Fill in Income and Expenses. Use the dropdowns in the Category, Method and Yes/No columns.
A3: INCOME | I3: MONTH SUMMARY
A4: Date | B4: Description | C4: Category | D4: Method | E4: Amount | F4: Received? | I4: Income | J4: =E25
I5: Expenses | J5: =F69
I6: Balance | J6: =J4-J5
I7: % saved | J7: =IFERROR(J6/J4,0)
I9: EXPENSES BY CATEGORY
I10: Category | J10: Amount | K10: %
I11: Housing | J11: =SUMIF($C$29:$C$68,$I11,$F$29:$F$68) | K11: =IFERROR(J11/$F$69,0)
I12: Bills | J12: =SUMIF($C$29:$C$68,$I12,$F$29:$F$68) | K12: =IFERROR(J12/$F$69,0)
I13: Groceries | J13: =SUMIF($C$29:$C$68,$I13,$F$29:$F$68) | K13: =IFERROR(J13/$F$69,0)
I14: Dining | J14: =SUMIF($C$29:$C$68,$I14,$F$29:$F$68) | K14: =IFERROR(J14/$F$69,0)
I15: Transport | J15: =SUMIF($C$29:$C$68,$I15,$F$29:$F$68) | K15: =IFERROR(J15/$F$69,0)
I16: Health | J16: =SUMIF($C$29:$C$68,$I16,$F$29:$F$68) | K16: =IFERROR(J16/$F$69,0)
I17: Education | J17: =SUMIF($C$29:$C$68,$I17,$F$29:$F$68) | K17: =IFERROR(J17/$F$69,0)
I18: Leisure | J18: =SUMIF($C$29:$C$68,$I18,$F$29:$F$68) | K18: =IFERROR(J18/$F$69,0)
I19: Clothing | J19: =SUMIF($C$29:$C$68,$I19,$F$29:$F$68) | K19: =IFERROR(J19/$F$69,0)
I20: Beauty | J20: =SUMIF($C$29:$C$68,$I20,$F$29:$F$68) | K20: =IFERROR(J20/$F$69,0)
I21: Subscriptions | J21: =SUMIF($C$29:$C$68,$I21,$F$29:$F$68) | K21: =IFERROR(J21/$F$69,0)
I22: Gifts | J22: =SUMIF($C$29:$C$68,$I22,$F$29:$F$68) | K22: =IFERROR(J22/$F$69,0)
... I24: Investments | J24: =SUMIF($C$29:$C$68,$I24,$F$29:$F$68) | K24: =IFERROR(J24/$F$69,0)
A25: TOTAL INCOME | E25: =SUM(E5:E24) | I25: Debt | J25: =SUMIF($C$29:$C$68,$I25,$F$29:$F$68) | K25: =IFERROR(J25/$F$69,0)
I26: Other | J26: =SUMIF($C$29:$C$68,$I26,$F$29:$F$68) | K26: =IFERROR(J26/$F$69,0)
A27: EXPENSES
A28: Date | B28: Description | C28: Category | D28: Type | E28: Method | F28: Amount | G28: Paid? | I28: EXPENSES BY PAYMENT METHOD
I29: Card | J29: =SUMIF($E$29:$E$68,$I29,$F$29:$F$68)
I30: Debit | J30: =SUMIF($E$29:$E$68,$I30,$F$29:$F$68)
I31: Cash | J31: =SUMIF($E$29:$E$68,$I31,$F$29:$F$68)
I32: Transfer | J32: =SUMIF($E$29:$E$68,$I32,$F$29:$F$68)
I33: PayPal | J33: =SUMIF($E$29:$E$68,$I33,$F$29:$F$68)
I34: Check | J34: =SUMIF($E$29:$E$68,$I34,$F$29:$F$68)
A69: TOTAL EXPENSES | F69: =SUM(F29:F68)

Sheet August
A1: AUGUST · Money Control · USUAL
A2: Fill in Income and Expenses. Use the dropdowns in the Category, Method and Yes/No columns.
A3: INCOME | I3: MONTH SUMMARY
A4: Date | B4: Description | C4: Category | D4: Method | E4: Amount | F4: Received? | I4: Income | J4: =E25
I5: Expenses | J5: =F69
I6: Balance | J6: =J4-J5
I7: % saved | J7: =IFERROR(J6/J4,0)
I9: EXPENSES BY CATEGORY
I10: Category | J10: Amount | K10: %
I11: Housing | J11: =SUMIF($C$29:$C$68,$I11,$F$29:$F$68) | K11: =IFERROR(J11/$F$69,0)
I12: Bills | J12: =SUMIF($C$29:$C$68,$I12,$F$29:$F$68) | K12: =IFERROR(J12/$F$69,0)
I13: Groceries | J13: =SUMIF($C$29:$C$68,$I13,$F$29:$F$68) | K13: =IFERROR(J13/$F$69,0)
I14: Dining | J14: =SUMIF($C$29:$C$68,$I14,$F$29:$F$68) | K14: =IFERROR(J14/$F$69,0)
I15: Transport | J15: =SUMIF($C$29:$C$68,$I15,$F$29:$F$68) | K15: =IFERROR(J15/$F$69,0)
I16: Health | J16: =SUMIF($C$29:$C$68,$I16,$F$29:$F$68) | K16: =IFERROR(J16/$F$69,0)
I17: Education | J17: =SUMIF($C$29:$C$68,$I17,$F$29:$F$68) | K17: =IFERROR(J17/$F$69,0)
I18: Leisure | J18: =SUMIF($C$29:$C$68,$I18,$F$29:$F$68) | K18: =IFERROR(J18/$F$69,0)
I19: Clothing | J19: =SUMIF($C$29:$C$68,$I19,$F$29:$F$68) | K19: =IFERROR(J19/$F$69,0)
I20: Beauty | J20: =SUMIF($C$29:$C$68,$I20,$F$29:$F$68) | K20: =IFERROR(J20/$F$69,0)
I21: Subscriptions | J21: =SUMIF($C$29:$C$68,$I21,$F$29:$F$68) | K21: =IFERROR(J21/$F$69,0)
I22: Gifts | J22: =SUMIF($C$29:$C$68,$I22,$F$29:$F$68) | K22: =IFERROR(J22/$F$69,0)
... I24: Investments | J24: =SUMIF($C$29:$C$68,$I24,$F$29:$F$68) | K24: =IFERROR(J24/$F$69,0)
A25: TOTAL INCOME | E25: =SUM(E5:E24) | I25: Debt | J25: =SUMIF($C$29:$C$68,$I25,$F$29:$F$68) | K25: =IFERROR(J25/$F$69,0)
I26: Other | J26: =SUMIF($C$29:$C$68,$I26,$F$29:$F$68) | K26: =IFERROR(J26/$F$69,0)
A27: EXPENSES
A28: Date | B28: Description | C28: Category | D28: Type | E28: Method | F28: Amount | G28: Paid? | I28: EXPENSES BY PAYMENT METHOD
I29: Card | J29: =SUMIF($E$29:$E$68,$I29,$F$29:$F$68)
I30: Debit | J30: =SUMIF($E$29:$E$68,$I30,$F$29:$F$68)
I31: Cash | J31: =SUMIF($E$29:$E$68,$I31,$F$29:$F$68)
I32: Transfer | J32: =SUMIF($E$29:$E$68,$I32,$F$29:$F$68)
I33: PayPal | J33: =SUMIF($E$29:$E$68,$I33,$F$29:$F$68)
I34: Check | J34: =SUMIF($E$29:$E$68,$I34,$F$29:$F$68)
A69: TOTAL EXPENSES | F69: =SUM(F29:F68)

Sheet September
A1: SEPTEMBER · Money Control · USUAL
A2: Fill in Income and Expenses. Use the dropdowns in the Category, Method and Yes/No columns.
A3: INCOME | I3: MONTH SUMMARY
A4: Date | B4: Description | C4: Category | D4: Method | E4: Amount | F4: Received? | I4: Income | J4: =E25
I5: Expenses | J5: =F69
I6: Balance | J6: =J4-J5
I7: % saved | J7: =IFERROR(J6/J4,0)
I9: EXPENSES BY CATEGORY
I10: Category | J10: Amount | K10: %
I11: Housing | J11: =SUMIF($C$29:$C$68,$I11,$F$29:$F$68) | K11: =IFERROR(J11/$F$69,0)
I12: Bills | J12: =SUMIF($C$29:$C$68,$I12,$F$29:$F$68) | K12: =IFERROR(J12/$F$69,0)
I13: Groceries | J13: =SUMIF($C$29:$C$68,$I13,$F$29:$F$68) | K13: =IFERROR(J13/$F$69,0)
I14: Dining | J14: =SUMIF($C$29:$C$68,$I14,$F$29:$F$68) | K14: =IFERROR(J14/$F$69,0)
I15: Transport | J15: =SUMIF($C$29:$C$68,$I15,$F$29:$F$68) | K15: =IFERROR(J15/$F$69,0)
I16: Health | J16: =SUMIF($C$29:$C$68,$I16,$F$29:$F$68) | K16: =IFERROR(J16/$F$69,0)
I17: Education | J17: =SUMIF($C$29:$C$68,$I17,$F$29:$F$68) | K17: =IFERROR(J17/$F$69,0)
I18: Leisure | J18: =SUMIF($C$29:$C$68,$I18,$F$29:$F$68) | K18: =IFERROR(J18/$F$69,0)
I19: Clothing | J19: =SUMIF($C$29:$C$68,$I19,$F$29:$F$68) | K19: =IFERROR(J19/$F$69,0)
I20: Beauty | J20: =SUMIF($C$29:$C$68,$I20,$F$29:$F$68) | K20: =IFERROR(J20/$F$69,0)
I21: Subscriptions | J21: =SUMIF($C$29:$C$68,$I21,$F$29:$F$68) | K21: =IFERROR(J21/$F$69,0)
I22: Gifts | J22: =SUMIF($C$29:$C$68,$I22,$F$29:$F$68) | K22: =IFERROR(J22/$F$69,0)
... I24: Investments | J24: =SUMIF($C$29:$C$68,$I24,$F$29:$F$68) | K24: =IFERROR(J24/$F$69,0)
A25: TOTAL INCOME | E25: =SUM(E5:E24) | I25: Debt | J25: =SUMIF($C$29:$C$68,$I25,$F$29:$F$68) | K25: =IFERROR(J25/$F$69,0)
I26: Other | J26: =SUMIF($C$29:$C$68,$I26,$F$29:$F$68) | K26: =IFERROR(J26/$F$69,0)
A27: EXPENSES
A28: Date | B28: Description | C28: Category | D28: Type | E28: Method | F28: Amount | G28: Paid? | I28: EXPENSES BY PAYMENT METHOD
I29: Card | J29: =SUMIF($E$29:$E$68,$I29,$F$29:$F$68)
I30: Debit | J30: =SUMIF($E$29:$E$68,$I30,$F$29:$F$68)
I31: Cash | J31: =SUMIF($E$29:$E$68,$I31,$F$29:$F$68)
I32: Transfer | J32: =SUMIF($E$29:$E$68,$I32,$F$29:$F$68)
I33: PayPal | J33: =SUMIF($E$29:$E$68,$I33,$F$29:$F$68)
I34: Check | J34: =SUMIF($E$29:$E$68,$I34,$F$29:$F$68)
A69: TOTAL EXPENSES | F69: =SUM(F29:F68)

Sheet October
A1: OCTOBER · Money Control · USUAL
A2: Fill in Income and Expenses. Use the dropdowns in the Category, Method and Yes/No columns.
A3: INCOME | I3: MONTH SUMMARY
A4: Date | B4: Description | C4: Category | D4: Method | E4: Amount | F4: Received? | I4: Income | J4: =E25
I5: Expenses | J5: =F69
I6: Balance | J6: =J4-J5
I7: % saved | J7: =IFERROR(J6/J4,0)
I9: EXPENSES BY CATEGORY
I10: Category | J10: Amount | K10: %
I11: Housing | J11: =SUMIF($C$29:$C$68,$I11,$F$29:$F$68) | K11: =IFERROR(J11/$F$69,0)
I12: Bills | J12: =SUMIF($C$29:$C$68,$I12,$F$29:$F$68) | K12: =IFERROR(J12/$F$69,0)
I13: Groceries | J13: =SUMIF($C$29:$C$68,$I13,$F$29:$F$68) | K13: =IFERROR(J13/$F$69,0)
I14: Dining | J14: =SUMIF($C$29:$C$68,$I14,$F$29:$F$68) | K14: =IFERROR(J14/$F$69,0)
I15: Transport | J15: =SUMIF($C$29:$C$68,$I15,$F$29:$F$68) | K15: =IFERROR(J15/$F$69,0)
I16: Health | J16: =SUMIF($C$29:$C$68,$I16,$F$29:$F$68) | K16: =IFERROR(J16/$F$69,0)
I17: Education | J17: =SUMIF($C$29:$C$68,$I17,$F$29:$F$68) | K17: =IFERROR(J17/$F$69,0)
I18: Leisure | J18: =SUMIF($C$29:$C$68,$I18,$F$29:$F$68) | K18: =IFERROR(J18/$F$69,0)
I19: Clothing | J19: =SUMIF($C$29:$C$68,$I19,$F$29:$F$68) | K19: =IFERROR(J19/$F$69,0)
I20: Beauty | J20: =SUMIF($C$29:$C$68,$I20,$F$29:$F$68) | K20: =IFERROR(J20/$F$69,0)
I21: Subscriptions | J21: =SUMIF($C$29:$C$68,$I21,$F$29:$F$68) | K21: =IFERROR(J21/$F$69,0)
I22: Gifts | J22: =SUMIF($C$29:$C$68,$I22,$F$29:$F$68) | K22: =IFERROR(J22/$F$69,0)
... I24: Investments | J24: =SUMIF($C$29:$C$68,$I24,$F$29:$F$68) | K24: =IFERROR(J24/$F$69,0)
A25: TOTAL INCOME | E25: =SUM(E5:E24) | I25: Debt | J25: =SUMIF($C$29:$C$68,$I25,$F$29:$F$68) | K25: =IFERROR(J25/$F$69,0)
I26: Other | J26: =SUMIF($C$29:$C$68,$I26,$F$29:$F$68) | K26: =IFERROR(J26/$F$69,0)
A27: EXPENSES
A28: Date | B28: Description | C28: Category | D28: Type | E28: Method | F28: Amount | G28: Paid? | I28: EXPENSES BY PAYMENT METHOD
I29: Card | J29: =SUMIF($E$29:$E$68,$I29,$F$29:$F$68)
I30: Debit | J30: =SUMIF($E$29:$E$68,$I30,$F$29:$F$68)
I31: Cash | J31: =SUMIF($E$29:$E$68,$I31,$F$29:$F$68)
I32: Transfer | J32: =SUMIF($E$29:$E$68,$I32,$F$29:$F$68)
I33: PayPal | J33: =SUMIF($E$29:$E$68,$I33,$F$29:$F$68)
I34: Check | J34: =SUMIF($E$29:$E$68,$I34,$F$29:$F$68)
A69: TOTAL EXPENSES | F69: =SUM(F29:F68)

Sheet November
A1: NOVEMBER · Money Control · USUAL
A2: Fill in Income and Expenses. Use the dropdowns in the Category, Method and Yes/No columns.
A3: INCOME | I3: MONTH SUMMARY
A4: Date | B4: Description | C4: Category | D4: Method | E4: Amount | F4: Received? | I4: Income | J4: =E25
I5: Expenses | J5: =F69
I6: Balance | J6: =J4-J5
I7: % saved | J7: =IFERROR(J6/J4,0)
I9: EXPENSES BY CATEGORY
I10: Category | J10: Amount | K10: %
I11: Housing | J11: =SUMIF($C$29:$C$68,$I11,$F$29:$F$68) | K11: =IFERROR(J11/$F$69,0)
I12: Bills | J12: =SUMIF($C$29:$C$68,$I12,$F$29:$F$68) | K12: =IFERROR(J12/$F$69,0)
I13: Groceries | J13: =SUMIF($C$29:$C$68,$I13,$F$29:$F$68) | K13: =IFERROR(J13/$F$69,0)
I14: Dining | J14: =SUMIF($C$29:$C$68,$I14,$F$29:$F$68) | K14: =IFERROR(J14/$F$69,0)
I15: Transport | J15: =SUMIF($C$29:$C$68,$I15,$F$29:$F$68) | K15: =IFERROR(J15/$F$69,0)
I16: Health | J16: =SUMIF($C$29:$C$68,$I16,$F$29:$F$68) | K16: =IFERROR(J16/$F$69,0)
I17: Education | J17: =SUMIF($C$29:$C$68,$I17,$F$29:$F$68) | K17: =IFERROR(J17/$F$69,0)
I18: Leisure | J18: =SUMIF($C$29:$C$68,$I18,$F$29:$F$68) | K18: =IFERROR(J18/$F$69,0)
I19: Clothing | J19: =SUMIF($C$29:$C$68,$I19,$F$29:$F$68) | K19: =IFERROR(J19/$F$69,0)
I20: Beauty | J20: =SUMIF($C$29:$C$68,$I20,$F$29:$F$68) | K20: =IFERROR(J20/$F$69,0)
I21: Subscriptions | J21: =SUMIF($C$29:$C$68,$I21,$F$29:$F$68) | K21: =IFERROR(J21/$F$69,0)
I22: Gifts | J22: =SUMIF($C$29:$C$68,$I22,$F$29:$F$68) | K22: =IFERROR(J22/$F$69,0)
... I24: Investments | J24: =SUMIF($C$29:$C$68,$I24,$F$29:$F$68) | K24: =IFERROR(J24/$F$69,0)
A25: TOTAL INCOME | E25: =SUM(E5:E24) | I25: Debt | J25: =SUMIF($C$29:$C$68,$I25,$F$29:$F$68) | K25: =IFERROR(J25/$F$69,0)
I26: Other | J26: =SUMIF($C$29:$C$68,$I26,$F$29:$F$68) | K26: =IFERROR(J26/$F$69,0)
A27: EXPENSES
A28: Date | B28: Description | C28: Category | D28: Type | E28: Method | F28: Amount | G28: Paid? | I28: EXPENSES BY PAYMENT METHOD
I29: Card | J29: =SUMIF($E$29:$E$68,$I29,$F$29:$F$68)
I30: Debit | J30: =SUMIF($E$29:$E$68,$I30,$F$29:$F$68)
I31: Cash | J31: =SUMIF($E$29:$E$68,$I31,$F$29:$F$68)
I32: Transfer | J32: =SUMIF($E$29:$E$68,$I32,$F$29:$F$68)
I33: PayPal | J33: =SUMIF($E$29:$E$68,$I33,$F$29:$F$68)
I34: Check | J34: =SUMIF($E$29:$E$68,$I34,$F$29:$F$68)
A69: TOTAL EXPENSES | F69: =SUM(F29:F68)

Sheet December
A1: DECEMBER · Money Control · USUAL
A2: Fill in Income and Expenses. Use the dropdowns in the Category, Method and Yes/No columns.
A3: INCOME | I3: MONTH SUMMARY
A4: Date | B4: Description | C4: Category | D4: Method | E4: Amount | F4: Received? | I4: Income | J4: =E25
I5: Expenses | J5: =F69
I6: Balance | J6: =J4-J5
I7: % saved | J7: =IFERROR(J6/J4,0)
I9: EXPENSES BY CATEGORY
I10: Category | J10: Amount | K10: %
I11: Housing | J11: =SUMIF($C$29:$C$68,$I11,$F$29:$F$68) | K11: =IFERROR(J11/$F$69,0)
I12: Bills | J12: =SUMIF($C$29:$C$68,$I12,$F$29:$F$68) | K12: =IFERROR(J12/$F$69,0)
I13: Groceries | J13: =SUMIF($C$29:$C$68,$I13,$F$29:$F$68) | K13: =IFERROR(J13/$F$69,0)
I14: Dining | J14: =SUMIF($C$29:$C$68,$I14,$F$29:$F$68) | K14: =IFERROR(J14/$F$69,0)
I15: Transport | J15: =SUMIF($C$29:$C$68,$I15,$F$29:$F$68) | K15: =IFERROR(J15/$F$69,0)
I16: Health | J16: =SUMIF($C$29:$C$68,$I16,$F$29:$F$68) | K16: =IFERROR(J16/$F$69,0)
I17: Education | J17: =SUMIF($C$29:$C$68,$I17,$F$29:$F$68) | K17: =IFERROR(J17/$F$69,0)
I18: Leisure | J18: =SUMIF($C$29:$C$68,$I18,$F$29:$F$68) | K18: =IFERROR(J18/$F$69,0)
I19: Clothing | J19: =SUMIF($C$29:$C$68,$I19,$F$29:$F$68) | K19: =IFERROR(J19/$F$69,0)
I20: Beauty | J20: =SUMIF($C$29:$C$68,$I20,$F$29:$F$68) | K20: =IFERROR(J20/$F$69,0)
I21: Subscriptions | J21: =SUMIF($C$29:$C$68,$I21,$F$29:$F$68) | K21: =IFERROR(J21/$F$69,0)
I22: Gifts | J22: =SUMIF($C$29:$C$68,$I22,$F$29:$F$68) | K22: =IFERROR(J22/$F$69,0)
... I24: Investments | J24: =SUMIF($C$29:$C$68,$I24,$F$29:$F$68) | K24: =IFERROR(J24/$F$69,0)
A25: TOTAL INCOME | E25: =SUM(E5:E24) | I25: Debt | J25: =SUMIF($C$29:$C$68,$I25,$F$29:$F$68) | K25: =IFERROR(J25/$F$69,0)
I26: Other | J26: =SUMIF($C$29:$C$68,$I26,$F$29:$F$68) | K26: =IFERROR(J26/$F$69,0)
A27: EXPENSES
A28: Date | B28: Description | C28: Category | D28: Type | E28: Method | F28: Amount | G28: Paid? | I28: EXPENSES BY PAYMENT METHOD
I29: Card | J29: =SUMIF($E$29:$E$68,$I29,$F$29:$F$68)
I30: Debit | J30: =SUMIF($E$29:$E$68,$I30,$F$29:$F$68)
I31: Cash | J31: =SUMIF($E$29:$E$68,$I31,$F$29:$F$68)
I32: Transfer | J32: =SUMIF($E$29:$E$68,$I32,$F$29:$F$68)
I33: PayPal | J33: =SUMIF($E$29:$E$68,$I33,$F$29:$F$68)
I34: Check | J34: =SUMIF($E$29:$E$68,$I34,$F$29:$F$68)
A69: TOTAL EXPENSES | F69: =SUM(F29:F68)

Sheet Financial Goals
A1: FINANCIAL GOALS · USUAL
A2: Set your goals and track how much is left for each.
B4: Goal | C4: Target amount | D4: Saved so far | E4: Remaining | F4: % complete | G4: Deadline
E5: =MAX(C5-D5,0) | F5: =IFERROR(D5/C5,0)
E6: =MAX(C6-D6,0) | F6: =IFERROR(D6/C6,0)
E7: =MAX(C7-D7,0) | F7: =IFERROR(D7/C7,0)
E8: =MAX(C8-D8,0) | F8: =IFERROR(D8/C8,0)
E9: =MAX(C9-D9,0) | F9: =IFERROR(D9/C9,0)
E10: =MAX(C10-D10,0) | F10: =IFERROR(D10/C10,0)
E11: =MAX(C11-D11,0) | F11: =IFERROR(D11/C11,0)
E12: =MAX(C12-D12,0) | F12: =IFERROR(D12/C12,0)
B13: TOTAL | C13: =SUM(C5:C12) | D13: =SUM(D5:D12) | E13: =SUM(E5:E12) | F13: =IFERROR(D13/C13,0)

Sheet Investments
A1: INVESTMENTS & RESERVES · USUAL
A2: Track how much you accumulate each month.
B4: Month | C4: Emergency fund | D4: Fixed income | E4: Variable income | F4: Total
B5: January | F5: =SUM(C5:E5)
B6: February | F6: =SUM(C6:E6)
B7: March | F7: =SUM(C7:E7)
B8: April | F8: =SUM(C8:E8)
B9: May | F9: =SUM(C9:E9)
B10: June | F10: =SUM(C10:E10)
B11: July | F11: =SUM(C11:E11)
B12: August | F12: =SUM(C12:E12)
B13: September | F13: =SUM(C13:E13)
B14: October | F14: =SUM(C14:E14)
B15: November | F15: =SUM(C15:E15)
B16: December | F16: =SUM(C16:E16)
B17: TOTAL | C17: =SUM(C5:C16) | D17: =SUM(D5:D16) | E17: =SUM(E5:E16) | F17: =SUM(F5:F16)

Sheet Categories
A1: CATEGORIES · USUAL
A2: Reference for the categories used in the months. Edit to your reality.
B4: EXPENSE categories | C4: INCOME categories
B5: Housing | C5: Salary
B6: Bills | C6: Owner's draw
B7: Groceries | C7: Sales
B8: Dining | C8: Freelance
B9: Transport | C9: Investment income
B10: Health | C10: Other
B11: Education
B12: Leisure
B13: Clothing
B14: Beauty
B15: Subscriptions
B16: Gifts
B17: Taxes
B18: Investments
B19: Debt
B20: Other

Sheet Accounts
A1: ACCOUNTS · USUAL
A2: Save the accounts you use most (blank template).
B4: Name | C4: Account / details | D4: Bank
