Workbook

Sheet Comece aqui
A1: PLANILHA DE GESTÃO FINANCEIRA · USUAL DIGITAL
A2: Um bônus para você organizar sua vida financeira e fazer seu dinheiro render.
B5: Como usar
B7: 1. Vá em cada mês (abas Janeiro a Dezembro) e lance suas Entradas e Despesas.
B8: 2. Use os menus suspensos para escolher Categoria, Forma de pagamento e Sim/Não.
B9: 3. Os totais, o saldo e os gráficos por categoria são calculados automaticamente.
B10: 4. Acompanhe o ano inteiro na aba Resumo Anual (puxa tudo dos meses).
B11: 5. Defina objetivos na aba Metas Financeiras e acompanhe seus Investimentos.
B12: 6. Guarde suas chaves PIX favoritas na aba Chaves PIX.
B14: Dica de ouro
B15: Lance os gastos no mesmo dia. 5 minutos por dia valem mais que 3 horas no fim do mês. O que não é medido não é gerenciado.
B17: Bônus oferecido por Mentor Gabriel Isidoro · Especialista em Estruturação Comercial · WhatsApp (14) 99876-0335

Sheet Resumo Anual
A1: RESUMO ANUAL · USUAL
A2: Os valores são puxados automaticamente de cada mês. Não precisa preencher aqui.
B3: Entradas no ano | C3: Despesas no ano | D3: Saldo no ano | E3: % poupado
B4: =C19 | C4: =D19 | D4: =E19 | E4: =IFERROR(E19/C19,0)
B6: Mês | C6: Entradas | D6: Despesas | E6: Saldo | F6: % poupado
B7: Janeiro | C7: ='Janeiro'!J4 | D7: ='Janeiro'!J5 | E7: =C7-D7 | F7: =IFERROR(E7/C7,0)
B8: Fevereiro | C8: ='Fevereiro'!J4 | D8: ='Fevereiro'!J5 | E8: =C8-D8 | F8: =IFERROR(E8/C8,0)
B9: Março | C9: ='Março'!J4 | D9: ='Março'!J5 | E9: =C9-D9 | F9: =IFERROR(E9/C9,0)
B10: Abril | C10: ='Abril'!J4 | D10: ='Abril'!J5 | E10: =C10-D10 | F10: =IFERROR(E10/C10,0)
B11: Maio | C11: ='Maio'!J4 | D11: ='Maio'!J5 | E11: =C11-D11 | F11: =IFERROR(E11/C11,0)
B12: Junho | C12: ='Junho'!J4 | D12: ='Junho'!J5 | E12: =C12-D12 | F12: =IFERROR(E12/C12,0)
B13: Julho | C13: ='Julho'!J4 | D13: ='Julho'!J5 | E13: =C13-D13 | F13: =IFERROR(E13/C13,0)
B14: Agosto | C14: ='Agosto'!J4 | D14: ='Agosto'!J5 | E14: =C14-D14 | F14: =IFERROR(E14/C14,0)
B15: Setembro | C15: ='Setembro'!J4 | D15: ='Setembro'!J5 | E15: =C15-D15 | F15: =IFERROR(E15/C15,0)
B16: Outubro | C16: ='Outubro'!J4 | D16: ='Outubro'!J5 | E16: =C16-D16 | F16: =IFERROR(E16/C16,0)
B17: Novembro | C17: ='Novembro'!J4 | D17: ='Novembro'!J5 | E17: =C17-D17 | F17: =IFERROR(E17/C17,0)
B18: Dezembro | C18: ='Dezembro'!J4 | D18: ='Dezembro'!J5 | E18: =C18-D18 | F18: =IFERROR(E18/C18,0)
B19: TOTAL | C19: =SUM(C7:C18) | D19: =SUM(D7:D18) | E19: =SUM(E7:E18) | F19: =IFERROR(E19/C19,0)

Sheet Janeiro
A1: JANEIRO · Controle Financeiro · USUAL
A2: Preencha Entradas e Despesas. Use os menus (dropdown) nas colunas de categoria, forma e Sim/Não.
A3: ENTRADAS | I3: RESUMO DO MÊS
A4: Data | B4: Descrição | C4: Categoria | D4: Forma | E4: Valor | F4: Recebido? | I4: Entradas | J4: =E25
I5: Despesas | J5: =F69
I6: Saldo | J6: =J4-J5
I7: % poupado | J7: =IFERROR(J6/J4,0)
I9: DESPESAS POR CATEGORIA
I10: Categoria | J10: Valor | K10: %
I11: Moradia | J11: =SUMIF($C$29:$C$68,$I11,$F$29:$F$68) | K11: =IFERROR(J11/$F$69,0)
I12: Contas | J12: =SUMIF($C$29:$C$68,$I12,$F$29:$F$68) | K12: =IFERROR(J12/$F$69,0)
I13: Mercado | J13: =SUMIF($C$29:$C$68,$I13,$F$29:$F$68) | K13: =IFERROR(J13/$F$69,0)
I14: Alimentação | J14: =SUMIF($C$29:$C$68,$I14,$F$29:$F$68) | K14: =IFERROR(J14/$F$69,0)
I15: Transporte | J15: =SUMIF($C$29:$C$68,$I15,$F$29:$F$68) | K15: =IFERROR(J15/$F$69,0)
I16: Saúde | J16: =SUMIF($C$29:$C$68,$I16,$F$29:$F$68) | K16: =IFERROR(J16/$F$69,0)
I17: Educação | J17: =SUMIF($C$29:$C$68,$I17,$F$29:$F$68) | K17: =IFERROR(J17/$F$69,0)
I18: Lazer | J18: =SUMIF($C$29:$C$68,$I18,$F$29:$F$68) | K18: =IFERROR(J18/$F$69,0)
I19: Vestuário | J19: =SUMIF($C$29:$C$68,$I19,$F$29:$F$68) | K19: =IFERROR(J19/$F$69,0)
I20: Beleza | J20: =SUMIF($C$29:$C$68,$I20,$F$29:$F$68) | K20: =IFERROR(J20/$F$69,0)
I21: Assinaturas | J21: =SUMIF($C$29:$C$68,$I21,$F$29:$F$68) | K21: =IFERROR(J21/$F$69,0)
I22: Presentes | J22: =SUMIF($C$29:$C$68,$I22,$F$29:$F$68) | K22: =IFERROR(J22/$F$69,0)
... I24: Investimentos | J24: =SUMIF($C$29:$C$68,$I24,$F$29:$F$68) | K24: =IFERROR(J24/$F$69,0)
A25: TOTAL DE ENTRADAS | E25: =SUM(E5:E24) | I25: Dívidas | J25: =SUMIF($C$29:$C$68,$I25,$F$29:$F$68) | K25: =IFERROR(J25/$F$69,0)
I26: Outros | J26: =SUMIF($C$29:$C$68,$I26,$F$29:$F$68) | K26: =IFERROR(J26/$F$69,0)
A27: DESPESAS
A28: Data | B28: Descrição | C28: Categoria | D28: Tipo | E28: Forma | F28: Valor | G28: Pago? | I28: DESPESAS POR FORMA DE PAGAMENTO
I29: Pix | J29: =SUMIF($E$29:$E$68,$I29,$F$29:$F$68)
I30: Débito | J30: =SUMIF($E$29:$E$68,$I30,$F$29:$F$68)
I31: Crédito | J31: =SUMIF($E$29:$E$68,$I31,$F$29:$F$68)
I32: Dinheiro | J32: =SUMIF($E$29:$E$68,$I32,$F$29:$F$68)
I33: Boleto | J33: =SUMIF($E$29:$E$68,$I33,$F$29:$F$68)
I34: Transferência | J34: =SUMIF($E$29:$E$68,$I34,$F$29:$F$68)
A69: TOTAL DE DESPESAS | F69: =SUM(F29:F68)

Sheet Fevereiro
A1: FEVEREIRO · Controle Financeiro · USUAL
A2: Preencha Entradas e Despesas. Use os menus (dropdown) nas colunas de categoria, forma e Sim/Não.
A3: ENTRADAS | I3: RESUMO DO MÊS
A4: Data | B4: Descrição | C4: Categoria | D4: Forma | E4: Valor | F4: Recebido? | I4: Entradas | J4: =E25
I5: Despesas | J5: =F69
I6: Saldo | J6: =J4-J5
I7: % poupado | J7: =IFERROR(J6/J4,0)
I9: DESPESAS POR CATEGORIA
I10: Categoria | J10: Valor | K10: %
I11: Moradia | J11: =SUMIF($C$29:$C$68,$I11,$F$29:$F$68) | K11: =IFERROR(J11/$F$69,0)
I12: Contas | J12: =SUMIF($C$29:$C$68,$I12,$F$29:$F$68) | K12: =IFERROR(J12/$F$69,0)
I13: Mercado | J13: =SUMIF($C$29:$C$68,$I13,$F$29:$F$68) | K13: =IFERROR(J13/$F$69,0)
I14: Alimentação | J14: =SUMIF($C$29:$C$68,$I14,$F$29:$F$68) | K14: =IFERROR(J14/$F$69,0)
I15: Transporte | J15: =SUMIF($C$29:$C$68,$I15,$F$29:$F$68) | K15: =IFERROR(J15/$F$69,0)
I16: Saúde | J16: =SUMIF($C$29:$C$68,$I16,$F$29:$F$68) | K16: =IFERROR(J16/$F$69,0)
I17: Educação | J17: =SUMIF($C$29:$C$68,$I17,$F$29:$F$68) | K17: =IFERROR(J17/$F$69,0)
I18: Lazer | J18: =SUMIF($C$29:$C$68,$I18,$F$29:$F$68) | K18: =IFERROR(J18/$F$69,0)
I19: Vestuário | J19: =SUMIF($C$29:$C$68,$I19,$F$29:$F$68) | K19: =IFERROR(J19/$F$69,0)
I20: Beleza | J20: =SUMIF($C$29:$C$68,$I20,$F$29:$F$68) | K20: =IFERROR(J20/$F$69,0)
I21: Assinaturas | J21: =SUMIF($C$29:$C$68,$I21,$F$29:$F$68) | K21: =IFERROR(J21/$F$69,0)
I22: Presentes | J22: =SUMIF($C$29:$C$68,$I22,$F$29:$F$68) | K22: =IFERROR(J22/$F$69,0)
... I24: Investimentos | J24: =SUMIF($C$29:$C$68,$I24,$F$29:$F$68) | K24: =IFERROR(J24/$F$69,0)
A25: TOTAL DE ENTRADAS | E25: =SUM(E5:E24) | I25: Dívidas | J25: =SUMIF($C$29:$C$68,$I25,$F$29:$F$68) | K25: =IFERROR(J25/$F$69,0)
I26: Outros | J26: =SUMIF($C$29:$C$68,$I26,$F$29:$F$68) | K26: =IFERROR(J26/$F$69,0)
A27: DESPESAS
A28: Data | B28: Descrição | C28: Categoria | D28: Tipo | E28: Forma | F28: Valor | G28: Pago? | I28: DESPESAS POR FORMA DE PAGAMENTO
I29: Pix | J29: =SUMIF($E$29:$E$68,$I29,$F$29:$F$68)
I30: Débito | J30: =SUMIF($E$29:$E$68,$I30,$F$29:$F$68)
I31: Crédito | J31: =SUMIF($E$29:$E$68,$I31,$F$29:$F$68)
I32: Dinheiro | J32: =SUMIF($E$29:$E$68,$I32,$F$29:$F$68)
I33: Boleto | J33: =SUMIF($E$29:$E$68,$I33,$F$29:$F$68)
I34: Transferência | J34: =SUMIF($E$29:$E$68,$I34,$F$29:$F$68)
A69: TOTAL DE DESPESAS | F69: =SUM(F29:F68)

Sheet Março
A1: MARÇO · Controle Financeiro · USUAL
A2: Preencha Entradas e Despesas. Use os menus (dropdown) nas colunas de categoria, forma e Sim/Não.
A3: ENTRADAS | I3: RESUMO DO MÊS
A4: Data | B4: Descrição | C4: Categoria | D4: Forma | E4: Valor | F4: Recebido? | I4: Entradas | J4: =E25
I5: Despesas | J5: =F69
I6: Saldo | J6: =J4-J5
I7: % poupado | J7: =IFERROR(J6/J4,0)
I9: DESPESAS POR CATEGORIA
I10: Categoria | J10: Valor | K10: %
I11: Moradia | J11: =SUMIF($C$29:$C$68,$I11,$F$29:$F$68) | K11: =IFERROR(J11/$F$69,0)
I12: Contas | J12: =SUMIF($C$29:$C$68,$I12,$F$29:$F$68) | K12: =IFERROR(J12/$F$69,0)
I13: Mercado | J13: =SUMIF($C$29:$C$68,$I13,$F$29:$F$68) | K13: =IFERROR(J13/$F$69,0)
I14: Alimentação | J14: =SUMIF($C$29:$C$68,$I14,$F$29:$F$68) | K14: =IFERROR(J14/$F$69,0)
I15: Transporte | J15: =SUMIF($C$29:$C$68,$I15,$F$29:$F$68) | K15: =IFERROR(J15/$F$69,0)
I16: Saúde | J16: =SUMIF($C$29:$C$68,$I16,$F$29:$F$68) | K16: =IFERROR(J16/$F$69,0)
I17: Educação | J17: =SUMIF($C$29:$C$68,$I17,$F$29:$F$68) | K17: =IFERROR(J17/$F$69,0)
I18: Lazer | J18: =SUMIF($C$29:$C$68,$I18,$F$29:$F$68) | K18: =IFERROR(J18/$F$69,0)
I19: Vestuário | J19: =SUMIF($C$29:$C$68,$I19,$F$29:$F$68) | K19: =IFERROR(J19/$F$69,0)
I20: Beleza | J20: =SUMIF($C$29:$C$68,$I20,$F$29:$F$68) | K20: =IFERROR(J20/$F$69,0)
I21: Assinaturas | J21: =SUMIF($C$29:$C$68,$I21,$F$29:$F$68) | K21: =IFERROR(J21/$F$69,0)
I22: Presentes | J22: =SUMIF($C$29:$C$68,$I22,$F$29:$F$68) | K22: =IFERROR(J22/$F$69,0)
... I24: Investimentos | J24: =SUMIF($C$29:$C$68,$I24,$F$29:$F$68) | K24: =IFERROR(J24/$F$69,0)
A25: TOTAL DE ENTRADAS | E25: =SUM(E5:E24) | I25: Dívidas | J25: =SUMIF($C$29:$C$68,$I25,$F$29:$F$68) | K25: =IFERROR(J25/$F$69,0)
I26: Outros | J26: =SUMIF($C$29:$C$68,$I26,$F$29:$F$68) | K26: =IFERROR(J26/$F$69,0)
A27: DESPESAS
A28: Data | B28: Descrição | C28: Categoria | D28: Tipo | E28: Forma | F28: Valor | G28: Pago? | I28: DESPESAS POR FORMA DE PAGAMENTO
I29: Pix | J29: =SUMIF($E$29:$E$68,$I29,$F$29:$F$68)
I30: Débito | J30: =SUMIF($E$29:$E$68,$I30,$F$29:$F$68)
I31: Crédito | J31: =SUMIF($E$29:$E$68,$I31,$F$29:$F$68)
I32: Dinheiro | J32: =SUMIF($E$29:$E$68,$I32,$F$29:$F$68)
I33: Boleto | J33: =SUMIF($E$29:$E$68,$I33,$F$29:$F$68)
I34: Transferência | J34: =SUMIF($E$29:$E$68,$I34,$F$29:$F$68)
A69: TOTAL DE DESPESAS | F69: =SUM(F29:F68)

Sheet Abril
A1: ABRIL · Controle Financeiro · USUAL
A2: Preencha Entradas e Despesas. Use os menus (dropdown) nas colunas de categoria, forma e Sim/Não.
A3: ENTRADAS | I3: RESUMO DO MÊS
A4: Data | B4: Descrição | C4: Categoria | D4: Forma | E4: Valor | F4: Recebido? | I4: Entradas | J4: =E25
I5: Despesas | J5: =F69
I6: Saldo | J6: =J4-J5
I7: % poupado | J7: =IFERROR(J6/J4,0)
I9: DESPESAS POR CATEGORIA
I10: Categoria | J10: Valor | K10: %
I11: Moradia | J11: =SUMIF($C$29:$C$68,$I11,$F$29:$F$68) | K11: =IFERROR(J11/$F$69,0)
I12: Contas | J12: =SUMIF($C$29:$C$68,$I12,$F$29:$F$68) | K12: =IFERROR(J12/$F$69,0)
I13: Mercado | J13: =SUMIF($C$29:$C$68,$I13,$F$29:$F$68) | K13: =IFERROR(J13/$F$69,0)
I14: Alimentação | J14: =SUMIF($C$29:$C$68,$I14,$F$29:$F$68) | K14: =IFERROR(J14/$F$69,0)
I15: Transporte | J15: =SUMIF($C$29:$C$68,$I15,$F$29:$F$68) | K15: =IFERROR(J15/$F$69,0)
I16: Saúde | J16: =SUMIF($C$29:$C$68,$I16,$F$29:$F$68) | K16: =IFERROR(J16/$F$69,0)
I17: Educação | J17: =SUMIF($C$29:$C$68,$I17,$F$29:$F$68) | K17: =IFERROR(J17/$F$69,0)
I18: Lazer | J18: =SUMIF($C$29:$C$68,$I18,$F$29:$F$68) | K18: =IFERROR(J18/$F$69,0)
I19: Vestuário | J19: =SUMIF($C$29:$C$68,$I19,$F$29:$F$68) | K19: =IFERROR(J19/$F$69,0)
I20: Beleza | J20: =SUMIF($C$29:$C$68,$I20,$F$29:$F$68) | K20: =IFERROR(J20/$F$69,0)
I21: Assinaturas | J21: =SUMIF($C$29:$C$68,$I21,$F$29:$F$68) | K21: =IFERROR(J21/$F$69,0)
I22: Presentes | J22: =SUMIF($C$29:$C$68,$I22,$F$29:$F$68) | K22: =IFERROR(J22/$F$69,0)
... I24: Investimentos | J24: =SUMIF($C$29:$C$68,$I24,$F$29:$F$68) | K24: =IFERROR(J24/$F$69,0)
A25: TOTAL DE ENTRADAS | E25: =SUM(E5:E24) | I25: Dívidas | J25: =SUMIF($C$29:$C$68,$I25,$F$29:$F$68) | K25: =IFERROR(J25/$F$69,0)
I26: Outros | J26: =SUMIF($C$29:$C$68,$I26,$F$29:$F$68) | K26: =IFERROR(J26/$F$69,0)
A27: DESPESAS
A28: Data | B28: Descrição | C28: Categoria | D28: Tipo | E28: Forma | F28: Valor | G28: Pago? | I28: DESPESAS POR FORMA DE PAGAMENTO
I29: Pix | J29: =SUMIF($E$29:$E$68,$I29,$F$29:$F$68)
I30: Débito | J30: =SUMIF($E$29:$E$68,$I30,$F$29:$F$68)
I31: Crédito | J31: =SUMIF($E$29:$E$68,$I31,$F$29:$F$68)
I32: Dinheiro | J32: =SUMIF($E$29:$E$68,$I32,$F$29:$F$68)
I33: Boleto | J33: =SUMIF($E$29:$E$68,$I33,$F$29:$F$68)
I34: Transferência | J34: =SUMIF($E$29:$E$68,$I34,$F$29:$F$68)
A69: TOTAL DE DESPESAS | F69: =SUM(F29:F68)

Sheet Maio
A1: MAIO · Controle Financeiro · USUAL
A2: Preencha Entradas e Despesas. Use os menus (dropdown) nas colunas de categoria, forma e Sim/Não.
A3: ENTRADAS | I3: RESUMO DO MÊS
A4: Data | B4: Descrição | C4: Categoria | D4: Forma | E4: Valor | F4: Recebido? | I4: Entradas | J4: =E25
I5: Despesas | J5: =F69
I6: Saldo | J6: =J4-J5
I7: % poupado | J7: =IFERROR(J6/J4,0)
I9: DESPESAS POR CATEGORIA
I10: Categoria | J10: Valor | K10: %
I11: Moradia | J11: =SUMIF($C$29:$C$68,$I11,$F$29:$F$68) | K11: =IFERROR(J11/$F$69,0)
I12: Contas | J12: =SUMIF($C$29:$C$68,$I12,$F$29:$F$68) | K12: =IFERROR(J12/$F$69,0)
I13: Mercado | J13: =SUMIF($C$29:$C$68,$I13,$F$29:$F$68) | K13: =IFERROR(J13/$F$69,0)
I14: Alimentação | J14: =SUMIF($C$29:$C$68,$I14,$F$29:$F$68) | K14: =IFERROR(J14/$F$69,0)
I15: Transporte | J15: =SUMIF($C$29:$C$68,$I15,$F$29:$F$68) | K15: =IFERROR(J15/$F$69,0)
I16: Saúde | J16: =SUMIF($C$29:$C$68,$I16,$F$29:$F$68) | K16: =IFERROR(J16/$F$69,0)
I17: Educação | J17: =SUMIF($C$29:$C$68,$I17,$F$29:$F$68) | K17: =IFERROR(J17/$F$69,0)
I18: Lazer | J18: =SUMIF($C$29:$C$68,$I18,$F$29:$F$68) | K18: =IFERROR(J18/$F$69,0)
I19: Vestuário | J19: =SUMIF($C$29:$C$68,$I19,$F$29:$F$68) | K19: =IFERROR(J19/$F$69,0)
I20: Beleza | J20: =SUMIF($C$29:$C$68,$I20,$F$29:$F$68) | K20: =IFERROR(J20/$F$69,0)
I21: Assinaturas | J21: =SUMIF($C$29:$C$68,$I21,$F$29:$F$68) | K21: =IFERROR(J21/$F$69,0)
I22: Presentes | J22: =SUMIF($C$29:$C$68,$I22,$F$29:$F$68) | K22: =IFERROR(J22/$F$69,0)
... I24: Investimentos | J24: =SUMIF($C$29:$C$68,$I24,$F$29:$F$68) | K24: =IFERROR(J24/$F$69,0)
A25: TOTAL DE ENTRADAS | E25: =SUM(E5:E24) | I25: Dívidas | J25: =SUMIF($C$29:$C$68,$I25,$F$29:$F$68) | K25: =IFERROR(J25/$F$69,0)
I26: Outros | J26: =SUMIF($C$29:$C$68,$I26,$F$29:$F$68) | K26: =IFERROR(J26/$F$69,0)
A27: DESPESAS
A28: Data | B28: Descrição | C28: Categoria | D28: Tipo | E28: Forma | F28: Valor | G28: Pago? | I28: DESPESAS POR FORMA DE PAGAMENTO
I29: Pix | J29: =SUMIF($E$29:$E$68,$I29,$F$29:$F$68)
I30: Débito | J30: =SUMIF($E$29:$E$68,$I30,$F$29:$F$68)
I31: Crédito | J31: =SUMIF($E$29:$E$68,$I31,$F$29:$F$68)
I32: Dinheiro | J32: =SUMIF($E$29:$E$68,$I32,$F$29:$F$68)
I33: Boleto | J33: =SUMIF($E$29:$E$68,$I33,$F$29:$F$68)
I34: Transferência | J34: =SUMIF($E$29:$E$68,$I34,$F$29:$F$68)
A69: TOTAL DE DESPESAS | F69: =SUM(F29:F68)

Sheet Junho
A1: JUNHO · Controle Financeiro · USUAL
A2: Preencha Entradas e Despesas. Use os menus (dropdown) nas colunas de categoria, forma e Sim/Não.
A3: ENTRADAS | I3: RESUMO DO MÊS
A4: Data | B4: Descrição | C4: Categoria | D4: Forma | E4: Valor | F4: Recebido? | I4: Entradas | J4: =E25
I5: Despesas | J5: =F69
I6: Saldo | J6: =J4-J5
I7: % poupado | J7: =IFERROR(J6/J4,0)
I9: DESPESAS POR CATEGORIA
I10: Categoria | J10: Valor | K10: %
I11: Moradia | J11: =SUMIF($C$29:$C$68,$I11,$F$29:$F$68) | K11: =IFERROR(J11/$F$69,0)
I12: Contas | J12: =SUMIF($C$29:$C$68,$I12,$F$29:$F$68) | K12: =IFERROR(J12/$F$69,0)
I13: Mercado | J13: =SUMIF($C$29:$C$68,$I13,$F$29:$F$68) | K13: =IFERROR(J13/$F$69,0)
I14: Alimentação | J14: =SUMIF($C$29:$C$68,$I14,$F$29:$F$68) | K14: =IFERROR(J14/$F$69,0)
I15: Transporte | J15: =SUMIF($C$29:$C$68,$I15,$F$29:$F$68) | K15: =IFERROR(J15/$F$69,0)
I16: Saúde | J16: =SUMIF($C$29:$C$68,$I16,$F$29:$F$68) | K16: =IFERROR(J16/$F$69,0)
I17: Educação | J17: =SUMIF($C$29:$C$68,$I17,$F$29:$F$68) | K17: =IFERROR(J17/$F$69,0)
I18: Lazer | J18: =SUMIF($C$29:$C$68,$I18,$F$29:$F$68) | K18: =IFERROR(J18/$F$69,0)
I19: Vestuário | J19: =SUMIF($C$29:$C$68,$I19,$F$29:$F$68) | K19: =IFERROR(J19/$F$69,0)
I20: Beleza | J20: =SUMIF($C$29:$C$68,$I20,$F$29:$F$68) | K20: =IFERROR(J20/$F$69,0)
I21: Assinaturas | J21: =SUMIF($C$29:$C$68,$I21,$F$29:$F$68) | K21: =IFERROR(J21/$F$69,0)
I22: Presentes | J22: =SUMIF($C$29:$C$68,$I22,$F$29:$F$68) | K22: =IFERROR(J22/$F$69,0)
... I24: Investimentos | J24: =SUMIF($C$29:$C$68,$I24,$F$29:$F$68) | K24: =IFERROR(J24/$F$69,0)
A25: TOTAL DE ENTRADAS | E25: =SUM(E5:E24) | I25: Dívidas | J25: =SUMIF($C$29:$C$68,$I25,$F$29:$F$68) | K25: =IFERROR(J25/$F$69,0)
I26: Outros | J26: =SUMIF($C$29:$C$68,$I26,$F$29:$F$68) | K26: =IFERROR(J26/$F$69,0)
A27: DESPESAS
A28: Data | B28: Descrição | C28: Categoria | D28: Tipo | E28: Forma | F28: Valor | G28: Pago? | I28: DESPESAS POR FORMA DE PAGAMENTO
I29: Pix | J29: =SUMIF($E$29:$E$68,$I29,$F$29:$F$68)
I30: Débito | J30: =SUMIF($E$29:$E$68,$I30,$F$29:$F$68)
I31: Crédito | J31: =SUMIF($E$29:$E$68,$I31,$F$29:$F$68)
I32: Dinheiro | J32: =SUMIF($E$29:$E$68,$I32,$F$29:$F$68)
I33: Boleto | J33: =SUMIF($E$29:$E$68,$I33,$F$29:$F$68)
I34: Transferência | J34: =SUMIF($E$29:$E$68,$I34,$F$29:$F$68)
A69: TOTAL DE DESPESAS | F69: =SUM(F29:F68)

Sheet Julho
A1: JULHO · Controle Financeiro · USUAL
A2: Preencha Entradas e Despesas. Use os menus (dropdown) nas colunas de categoria, forma e Sim/Não.
A3: ENTRADAS | I3: RESUMO DO MÊS
A4: Data | B4: Descrição | C4: Categoria | D4: Forma | E4: Valor | F4: Recebido? | I4: Entradas | J4: =E25
I5: Despesas | J5: =F69
I6: Saldo | J6: =J4-J5
I7: % poupado | J7: =IFERROR(J6/J4,0)
I9: DESPESAS POR CATEGORIA
I10: Categoria | J10: Valor | K10: %
I11: Moradia | J11: =SUMIF($C$29:$C$68,$I11,$F$29:$F$68) | K11: =IFERROR(J11/$F$69,0)
I12: Contas | J12: =SUMIF($C$29:$C$68,$I12,$F$29:$F$68) | K12: =IFERROR(J12/$F$69,0)
I13: Mercado | J13: =SUMIF($C$29:$C$68,$I13,$F$29:$F$68) | K13: =IFERROR(J13/$F$69,0)
I14: Alimentação | J14: =SUMIF($C$29:$C$68,$I14,$F$29:$F$68) | K14: =IFERROR(J14/$F$69,0)
I15: Transporte | J15: =SUMIF($C$29:$C$68,$I15,$F$29:$F$68) | K15: =IFERROR(J15/$F$69,0)
I16: Saúde | J16: =SUMIF($C$29:$C$68,$I16,$F$29:$F$68) | K16: =IFERROR(J16/$F$69,0)
I17: Educação | J17: =SUMIF($C$29:$C$68,$I17,$F$29:$F$68) | K17: =IFERROR(J17/$F$69,0)
I18: Lazer | J18: =SUMIF($C$29:$C$68,$I18,$F$29:$F$68) | K18: =IFERROR(J18/$F$69,0)
I19: Vestuário | J19: =SUMIF($C$29:$C$68,$I19,$F$29:$F$68) | K19: =IFERROR(J19/$F$69,0)
I20: Beleza | J20: =SUMIF($C$29:$C$68,$I20,$F$29:$F$68) | K20: =IFERROR(J20/$F$69,0)
I21: Assinaturas | J21: =SUMIF($C$29:$C$68,$I21,$F$29:$F$68) | K21: =IFERROR(J21/$F$69,0)
I22: Presentes | J22: =SUMIF($C$29:$C$68,$I22,$F$29:$F$68) | K22: =IFERROR(J22/$F$69,0)
... I24: Investimentos | J24: =SUMIF($C$29:$C$68,$I24,$F$29:$F$68) | K24: =IFERROR(J24/$F$69,0)
A25: TOTAL DE ENTRADAS | E25: =SUM(E5:E24) | I25: Dívidas | J25: =SUMIF($C$29:$C$68,$I25,$F$29:$F$68) | K25: =IFERROR(J25/$F$69,0)
I26: Outros | J26: =SUMIF($C$29:$C$68,$I26,$F$29:$F$68) | K26: =IFERROR(J26/$F$69,0)
A27: DESPESAS
A28: Data | B28: Descrição | C28: Categoria | D28: Tipo | E28: Forma | F28: Valor | G28: Pago? | I28: DESPESAS POR FORMA DE PAGAMENTO
I29: Pix | J29: =SUMIF($E$29:$E$68,$I29,$F$29:$F$68)
I30: Débito | J30: =SUMIF($E$29:$E$68,$I30,$F$29:$F$68)
I31: Crédito | J31: =SUMIF($E$29:$E$68,$I31,$F$29:$F$68)
I32: Dinheiro | J32: =SUMIF($E$29:$E$68,$I32,$F$29:$F$68)
I33: Boleto | J33: =SUMIF($E$29:$E$68,$I33,$F$29:$F$68)
I34: Transferência | J34: =SUMIF($E$29:$E$68,$I34,$F$29:$F$68)
A69: TOTAL DE DESPESAS | F69: =SUM(F29:F68)

Sheet Agosto
A1: AGOSTO · Controle Financeiro · USUAL
A2: Preencha Entradas e Despesas. Use os menus (dropdown) nas colunas de categoria, forma e Sim/Não.
A3: ENTRADAS | I3: RESUMO DO MÊS
A4: Data | B4: Descrição | C4: Categoria | D4: Forma | E4: Valor | F4: Recebido? | I4: Entradas | J4: =E25
I5: Despesas | J5: =F69
I6: Saldo | J6: =J4-J5
I7: % poupado | J7: =IFERROR(J6/J4,0)
I9: DESPESAS POR CATEGORIA
I10: Categoria | J10: Valor | K10: %
I11: Moradia | J11: =SUMIF($C$29:$C$68,$I11,$F$29:$F$68) | K11: =IFERROR(J11/$F$69,0)
I12: Contas | J12: =SUMIF($C$29:$C$68,$I12,$F$29:$F$68) | K12: =IFERROR(J12/$F$69,0)
I13: Mercado | J13: =SUMIF($C$29:$C$68,$I13,$F$29:$F$68) | K13: =IFERROR(J13/$F$69,0)
I14: Alimentação | J14: =SUMIF($C$29:$C$68,$I14,$F$29:$F$68) | K14: =IFERROR(J14/$F$69,0)
I15: Transporte | J15: =SUMIF($C$29:$C$68,$I15,$F$29:$F$68) | K15: =IFERROR(J15/$F$69,0)
I16: Saúde | J16: =SUMIF($C$29:$C$68,$I16,$F$29:$F$68) | K16: =IFERROR(J16/$F$69,0)
I17: Educação | J17: =SUMIF($C$29:$C$68,$I17,$F$29:$F$68) | K17: =IFERROR(J17/$F$69,0)
I18: Lazer | J18: =SUMIF($C$29:$C$68,$I18,$F$29:$F$68) | K18: =IFERROR(J18/$F$69,0)
I19: Vestuário | J19: =SUMIF($C$29:$C$68,$I19,$F$29:$F$68) | K19: =IFERROR(J19/$F$69,0)
I20: Beleza | J20: =SUMIF($C$29:$C$68,$I20,$F$29:$F$68) | K20: =IFERROR(J20/$F$69,0)
I21: Assinaturas | J21: =SUMIF($C$29:$C$68,$I21,$F$29:$F$68) | K21: =IFERROR(J21/$F$69,0)
I22: Presentes | J22: =SUMIF($C$29:$C$68,$I22,$F$29:$F$68) | K22: =IFERROR(J22/$F$69,0)
... I24: Investimentos | J24: =SUMIF($C$29:$C$68,$I24,$F$29:$F$68) | K24: =IFERROR(J24/$F$69,0)
A25: TOTAL DE ENTRADAS | E25: =SUM(E5:E24) | I25: Dívidas | J25: =SUMIF($C$29:$C$68,$I25,$F$29:$F$68) | K25: =IFERROR(J25/$F$69,0)
I26: Outros | J26: =SUMIF($C$29:$C$68,$I26,$F$29:$F$68) | K26: =IFERROR(J26/$F$69,0)
A27: DESPESAS
A28: Data | B28: Descrição | C28: Categoria | D28: Tipo | E28: Forma | F28: Valor | G28: Pago? | I28: DESPESAS POR FORMA DE PAGAMENTO
I29: Pix | J29: =SUMIF($E$29:$E$68,$I29,$F$29:$F$68)
I30: Débito | J30: =SUMIF($E$29:$E$68,$I30,$F$29:$F$68)
I31: Crédito | J31: =SUMIF($E$29:$E$68,$I31,$F$29:$F$68)
I32: Dinheiro | J32: =SUMIF($E$29:$E$68,$I32,$F$29:$F$68)
I33: Boleto | J33: =SUMIF($E$29:$E$68,$I33,$F$29:$F$68)
I34: Transferência | J34: =SUMIF($E$29:$E$68,$I34,$F$29:$F$68)
A69: TOTAL DE DESPESAS | F69: =SUM(F29:F68)

Sheet Setembro
A1: SETEMBRO · Controle Financeiro · USUAL
A2: Preencha Entradas e Despesas. Use os menus (dropdown) nas colunas de categoria, forma e Sim/Não.
A3: ENTRADAS | I3: RESUMO DO MÊS
A4: Data | B4: Descrição | C4: Categoria | D4: Forma | E4: Valor | F4: Recebido? | I4: Entradas | J4: =E25
I5: Despesas | J5: =F69
I6: Saldo | J6: =J4-J5
I7: % poupado | J7: =IFERROR(J6/J4,0)
I9: DESPESAS POR CATEGORIA
I10: Categoria | J10: Valor | K10: %
I11: Moradia | J11: =SUMIF($C$29:$C$68,$I11,$F$29:$F$68) | K11: =IFERROR(J11/$F$69,0)
I12: Contas | J12: =SUMIF($C$29:$C$68,$I12,$F$29:$F$68) | K12: =IFERROR(J12/$F$69,0)
I13: Mercado | J13: =SUMIF($C$29:$C$68,$I13,$F$29:$F$68) | K13: =IFERROR(J13/$F$69,0)
I14: Alimentação | J14: =SUMIF($C$29:$C$68,$I14,$F$29:$F$68) | K14: =IFERROR(J14/$F$69,0)
I15: Transporte | J15: =SUMIF($C$29:$C$68,$I15,$F$29:$F$68) | K15: =IFERROR(J15/$F$69,0)
I16: Saúde | J16: =SUMIF($C$29:$C$68,$I16,$F$29:$F$68) | K16: =IFERROR(J16/$F$69,0)
I17: Educação | J17: =SUMIF($C$29:$C$68,$I17,$F$29:$F$68) | K17: =IFERROR(J17/$F$69,0)
I18: Lazer | J18: =SUMIF($C$29:$C$68,$I18,$F$29:$F$68) | K18: =IFERROR(J18/$F$69,0)
I19: Vestuário | J19: =SUMIF($C$29:$C$68,$I19,$F$29:$F$68) | K19: =IFERROR(J19/$F$69,0)
I20: Beleza | J20: =SUMIF($C$29:$C$68,$I20,$F$29:$F$68) | K20: =IFERROR(J20/$F$69,0)
I21: Assinaturas | J21: =SUMIF($C$29:$C$68,$I21,$F$29:$F$68) | K21: =IFERROR(J21/$F$69,0)
I22: Presentes | J22: =SUMIF($C$29:$C$68,$I22,$F$29:$F$68) | K22: =IFERROR(J22/$F$69,0)
... I24: Investimentos | J24: =SUMIF($C$29:$C$68,$I24,$F$29:$F$68) | K24: =IFERROR(J24/$F$69,0)
A25: TOTAL DE ENTRADAS | E25: =SUM(E5:E24) | I25: Dívidas | J25: =SUMIF($C$29:$C$68,$I25,$F$29:$F$68) | K25: =IFERROR(J25/$F$69,0)
I26: Outros | J26: =SUMIF($C$29:$C$68,$I26,$F$29:$F$68) | K26: =IFERROR(J26/$F$69,0)
A27: DESPESAS
A28: Data | B28: Descrição | C28: Categoria | D28: Tipo | E28: Forma | F28: Valor | G28: Pago? | I28: DESPESAS POR FORMA DE PAGAMENTO
I29: Pix | J29: =SUMIF($E$29:$E$68,$I29,$F$29:$F$68)
I30: Débito | J30: =SUMIF($E$29:$E$68,$I30,$F$29:$F$68)
I31: Crédito | J31: =SUMIF($E$29:$E$68,$I31,$F$29:$F$68)
I32: Dinheiro | J32: =SUMIF($E$29:$E$68,$I32,$F$29:$F$68)
I33: Boleto | J33: =SUMIF($E$29:$E$68,$I33,$F$29:$F$68)
I34: Transferência | J34: =SUMIF($E$29:$E$68,$I34,$F$29:$F$68)
A69: TOTAL DE DESPESAS | F69: =SUM(F29:F68)

Sheet Outubro
A1: OUTUBRO · Controle Financeiro · USUAL
A2: Preencha Entradas e Despesas. Use os menus (dropdown) nas colunas de categoria, forma e Sim/Não.
A3: ENTRADAS | I3: RESUMO DO MÊS
A4: Data | B4: Descrição | C4: Categoria | D4: Forma | E4: Valor | F4: Recebido? | I4: Entradas | J4: =E25
I5: Despesas | J5: =F69
I6: Saldo | J6: =J4-J5
I7: % poupado | J7: =IFERROR(J6/J4,0)
I9: DESPESAS POR CATEGORIA
I10: Categoria | J10: Valor | K10: %
I11: Moradia | J11: =SUMIF($C$29:$C$68,$I11,$F$29:$F$68) | K11: =IFERROR(J11/$F$69,0)
I12: Contas | J12: =SUMIF($C$29:$C$68,$I12,$F$29:$F$68) | K12: =IFERROR(J12/$F$69,0)
I13: Mercado | J13: =SUMIF($C$29:$C$68,$I13,$F$29:$F$68) | K13: =IFERROR(J13/$F$69,0)
I14: Alimentação | J14: =SUMIF($C$29:$C$68,$I14,$F$29:$F$68) | K14: =IFERROR(J14/$F$69,0)
I15: Transporte | J15: =SUMIF($C$29:$C$68,$I15,$F$29:$F$68) | K15: =IFERROR(J15/$F$69,0)
I16: Saúde | J16: =SUMIF($C$29:$C$68,$I16,$F$29:$F$68) | K16: =IFERROR(J16/$F$69,0)
I17: Educação | J17: =SUMIF($C$29:$C$68,$I17,$F$29:$F$68) | K17: =IFERROR(J17/$F$69,0)
I18: Lazer | J18: =SUMIF($C$29:$C$68,$I18,$F$29:$F$68) | K18: =IFERROR(J18/$F$69,0)
I19: Vestuário | J19: =SUMIF($C$29:$C$68,$I19,$F$29:$F$68) | K19: =IFERROR(J19/$F$69,0)
I20: Beleza | J20: =SUMIF($C$29:$C$68,$I20,$F$29:$F$68) | K20: =IFERROR(J20/$F$69,0)
I21: Assinaturas | J21: =SUMIF($C$29:$C$68,$I21,$F$29:$F$68) | K21: =IFERROR(J21/$F$69,0)
I22: Presentes | J22: =SUMIF($C$29:$C$68,$I22,$F$29:$F$68) | K22: =IFERROR(J22/$F$69,0)
... I24: Investimentos | J24: =SUMIF($C$29:$C$68,$I24,$F$29:$F$68) | K24: =IFERROR(J24/$F$69,0)
A25: TOTAL DE ENTRADAS | E25: =SUM(E5:E24) | I25: Dívidas | J25: =SUMIF($C$29:$C$68,$I25,$F$29:$F$68) | K25: =IFERROR(J25/$F$69,0)
I26: Outros | J26: =SUMIF($C$29:$C$68,$I26,$F$29:$F$68) | K26: =IFERROR(J26/$F$69,0)
A27: DESPESAS
A28: Data | B28: Descrição | C28: Categoria | D28: Tipo | E28: Forma | F28: Valor | G28: Pago? | I28: DESPESAS POR FORMA DE PAGAMENTO
I29: Pix | J29: =SUMIF($E$29:$E$68,$I29,$F$29:$F$68)
I30: Débito | J30: =SUMIF($E$29:$E$68,$I30,$F$29:$F$68)
I31: Crédito | J31: =SUMIF($E$29:$E$68,$I31,$F$29:$F$68)
I32: Dinheiro | J32: =SUMIF($E$29:$E$68,$I32,$F$29:$F$68)
I33: Boleto | J33: =SUMIF($E$29:$E$68,$I33,$F$29:$F$68)
I34: Transferência | J34: =SUMIF($E$29:$E$68,$I34,$F$29:$F$68)
A69: TOTAL DE DESPESAS | F69: =SUM(F29:F68)

Sheet Novembro
A1: NOVEMBRO · Controle Financeiro · USUAL
A2: Preencha Entradas e Despesas. Use os menus (dropdown) nas colunas de categoria, forma e Sim/Não.
A3: ENTRADAS | I3: RESUMO DO MÊS
A4: Data | B4: Descrição | C4: Categoria | D4: Forma | E4: Valor | F4: Recebido? | I4: Entradas | J4: =E25
I5: Despesas | J5: =F69
I6: Saldo | J6: =J4-J5
I7: % poupado | J7: =IFERROR(J6/J4,0)
I9: DESPESAS POR CATEGORIA
I10: Categoria | J10: Valor | K10: %
I11: Moradia | J11: =SUMIF($C$29:$C$68,$I11,$F$29:$F$68) | K11: =IFERROR(J11/$F$69,0)
I12: Contas | J12: =SUMIF($C$29:$C$68,$I12,$F$29:$F$68) | K12: =IFERROR(J12/$F$69,0)
I13: Mercado | J13: =SUMIF($C$29:$C$68,$I13,$F$29:$F$68) | K13: =IFERROR(J13/$F$69,0)
I14: Alimentação | J14: =SUMIF($C$29:$C$68,$I14,$F$29:$F$68) | K14: =IFERROR(J14/$F$69,0)
I15: Transporte | J15: =SUMIF($C$29:$C$68,$I15,$F$29:$F$68) | K15: =IFERROR(J15/$F$69,0)
I16: Saúde | J16: =SUMIF($C$29:$C$68,$I16,$F$29:$F$68) | K16: =IFERROR(J16/$F$69,0)
I17: Educação | J17: =SUMIF($C$29:$C$68,$I17,$F$29:$F$68) | K17: =IFERROR(J17/$F$69,0)
I18: Lazer | J18: =SUMIF($C$29:$C$68,$I18,$F$29:$F$68) | K18: =IFERROR(J18/$F$69,0)
I19: Vestuário | J19: =SUMIF($C$29:$C$68,$I19,$F$29:$F$68) | K19: =IFERROR(J19/$F$69,0)
I20: Beleza | J20: =SUMIF($C$29:$C$68,$I20,$F$29:$F$68) | K20: =IFERROR(J20/$F$69,0)
I21: Assinaturas | J21: =SUMIF($C$29:$C$68,$I21,$F$29:$F$68) | K21: =IFERROR(J21/$F$69,0)
I22: Presentes | J22: =SUMIF($C$29:$C$68,$I22,$F$29:$F$68) | K22: =IFERROR(J22/$F$69,0)
... I24: Investimentos | J24: =SUMIF($C$29:$C$68,$I24,$F$29:$F$68) | K24: =IFERROR(J24/$F$69,0)
A25: TOTAL DE ENTRADAS | E25: =SUM(E5:E24) | I25: Dívidas | J25: =SUMIF($C$29:$C$68,$I25,$F$29:$F$68) | K25: =IFERROR(J25/$F$69,0)
I26: Outros | J26: =SUMIF($C$29:$C$68,$I26,$F$29:$F$68) | K26: =IFERROR(J26/$F$69,0)
A27: DESPESAS
A28: Data | B28: Descrição | C28: Categoria | D28: Tipo | E28: Forma | F28: Valor | G28: Pago? | I28: DESPESAS POR FORMA DE PAGAMENTO
I29: Pix | J29: =SUMIF($E$29:$E$68,$I29,$F$29:$F$68)
I30: Débito | J30: =SUMIF($E$29:$E$68,$I30,$F$29:$F$68)
I31: Crédito | J31: =SUMIF($E$29:$E$68,$I31,$F$29:$F$68)
I32: Dinheiro | J32: =SUMIF($E$29:$E$68,$I32,$F$29:$F$68)
I33: Boleto | J33: =SUMIF($E$29:$E$68,$I33,$F$29:$F$68)
I34: Transferência | J34: =SUMIF($E$29:$E$68,$I34,$F$29:$F$68)
A69: TOTAL DE DESPESAS | F69: =SUM(F29:F68)

Sheet Dezembro
A1: DEZEMBRO · Controle Financeiro · USUAL
A2: Preencha Entradas e Despesas. Use os menus (dropdown) nas colunas de categoria, forma e Sim/Não.
A3: ENTRADAS | I3: RESUMO DO MÊS
A4: Data | B4: Descrição | C4: Categoria | D4: Forma | E4: Valor | F4: Recebido? | I4: Entradas | J4: =E25
I5: Despesas | J5: =F69
I6: Saldo | J6: =J4-J5
I7: % poupado | J7: =IFERROR(J6/J4,0)
I9: DESPESAS POR CATEGORIA
I10: Categoria | J10: Valor | K10: %
I11: Moradia | J11: =SUMIF($C$29:$C$68,$I11,$F$29:$F$68) | K11: =IFERROR(J11/$F$69,0)
I12: Contas | J12: =SUMIF($C$29:$C$68,$I12,$F$29:$F$68) | K12: =IFERROR(J12/$F$69,0)
I13: Mercado | J13: =SUMIF($C$29:$C$68,$I13,$F$29:$F$68) | K13: =IFERROR(J13/$F$69,0)
I14: Alimentação | J14: =SUMIF($C$29:$C$68,$I14,$F$29:$F$68) | K14: =IFERROR(J14/$F$69,0)
I15: Transporte | J15: =SUMIF($C$29:$C$68,$I15,$F$29:$F$68) | K15: =IFERROR(J15/$F$69,0)
I16: Saúde | J16: =SUMIF($C$29:$C$68,$I16,$F$29:$F$68) | K16: =IFERROR(J16/$F$69,0)
I17: Educação | J17: =SUMIF($C$29:$C$68,$I17,$F$29:$F$68) | K17: =IFERROR(J17/$F$69,0)
I18: Lazer | J18: =SUMIF($C$29:$C$68,$I18,$F$29:$F$68) | K18: =IFERROR(J18/$F$69,0)
I19: Vestuário | J19: =SUMIF($C$29:$C$68,$I19,$F$29:$F$68) | K19: =IFERROR(J19/$F$69,0)
I20: Beleza | J20: =SUMIF($C$29:$C$68,$I20,$F$29:$F$68) | K20: =IFERROR(J20/$F$69,0)
I21: Assinaturas | J21: =SUMIF($C$29:$C$68,$I21,$F$29:$F$68) | K21: =IFERROR(J21/$F$69,0)
I22: Presentes | J22: =SUMIF($C$29:$C$68,$I22,$F$29:$F$68) | K22: =IFERROR(J22/$F$69,0)
... I24: Investimentos | J24: =SUMIF($C$29:$C$68,$I24,$F$29:$F$68) | K24: =IFERROR(J24/$F$69,0)
A25: TOTAL DE ENTRADAS | E25: =SUM(E5:E24) | I25: Dívidas | J25: =SUMIF($C$29:$C$68,$I25,$F$29:$F$68) | K25: =IFERROR(J25/$F$69,0)
I26: Outros | J26: =SUMIF($C$29:$C$68,$I26,$F$29:$F$68) | K26: =IFERROR(J26/$F$69,0)
A27: DESPESAS
A28: Data | B28: Descrição | C28: Categoria | D28: Tipo | E28: Forma | F28: Valor | G28: Pago? | I28: DESPESAS POR FORMA DE PAGAMENTO
I29: Pix | J29: =SUMIF($E$29:$E$68,$I29,$F$29:$F$68)
I30: Débito | J30: =SUMIF($E$29:$E$68,$I30,$F$29:$F$68)
I31: Crédito | J31: =SUMIF($E$29:$E$68,$I31,$F$29:$F$68)
I32: Dinheiro | J32: =SUMIF($E$29:$E$68,$I32,$F$29:$F$68)
I33: Boleto | J33: =SUMIF($E$29:$E$68,$I33,$F$29:$F$68)
I34: Transferência | J34: =SUMIF($E$29:$E$68,$I34,$F$29:$F$68)
A69: TOTAL DE DESPESAS | F69: =SUM(F29:F68)

Sheet Metas Financeiras
A1: METAS FINANCEIRAS · USUAL
A2: Defina seus objetivos e acompanhe o quanto falta para cada um.
B4: Objetivo | C4: Valor da meta | D4: Já guardado | E4: Falta | F4: % concluído | G4: Prazo
E5: =MAX(C5-D5,0) | F5: =IFERROR(D5/C5,0)
E6: =MAX(C6-D6,0) | F6: =IFERROR(D6/C6,0)
E7: =MAX(C7-D7,0) | F7: =IFERROR(D7/C7,0)
E8: =MAX(C8-D8,0) | F8: =IFERROR(D8/C8,0)
E9: =MAX(C9-D9,0) | F9: =IFERROR(D9/C9,0)
E10: =MAX(C10-D10,0) | F10: =IFERROR(D10/C10,0)
E11: =MAX(C11-D11,0) | F11: =IFERROR(D11/C11,0)
E12: =MAX(C12-D12,0) | F12: =IFERROR(D12/C12,0)
B13: TOTAL | C13: =SUM(C5:C12) | D13: =SUM(D5:D12) | E13: =SUM(E5:E12) | F13: =IFERROR(D13/C13,0)

Sheet Investimentos
A1: INVESTIMENTOS E RESERVAS · USUAL
A2: Acompanhe quanto você acumula por mês.
B4: Mês | C4: Reserva de emergência | D4: Renda fixa | E4: Renda variável | F4: Total
B5: Janeiro | F5: =SUM(C5:E5)
B6: Fevereiro | F6: =SUM(C6:E6)
B7: Março | F7: =SUM(C7:E7)
B8: Abril | F8: =SUM(C8:E8)
B9: Maio | F9: =SUM(C9:E9)
B10: Junho | F10: =SUM(C10:E10)
B11: Julho | F11: =SUM(C11:E11)
B12: Agosto | F12: =SUM(C12:E12)
B13: Setembro | F13: =SUM(C13:E13)
B14: Outubro | F14: =SUM(C14:E14)
B15: Novembro | F15: =SUM(C15:E15)
B16: Dezembro | F16: =SUM(C16:E16)
B17: TOTAL | C17: =SUM(C5:C16) | D17: =SUM(D5:D16) | E17: =SUM(E5:E16) | F17: =SUM(F5:F16)

Sheet Categorias
A1: CATEGORIAS · USUAL
A2: Referência das categorias usadas nos meses. Edite conforme a sua realidade.
B4: Categorias de DESPESA | C4: Categorias de RECEITA
B5: Moradia | C5: Salário
B6: Contas | C6: Pró-labore
B7: Mercado | C7: Vendas
B8: Alimentação | C8: Freelas
B9: Transporte | C9: Rendimentos
B10: Saúde | C10: Outros
B11: Educação
B12: Lazer
B13: Vestuário
B14: Beleza
B15: Assinaturas
B16: Presentes
B17: Impostos
B18: Investimentos
B19: Dívidas
B20: Outros

Sheet Chaves PIX
A1: CHAVES PIX · USUAL
A2: Guarde aqui as chaves PIX que você mais usa (modelo em branco).
B4: Nome | C4: Chave PIX | D4: Banco
